[
{"name": "Aspiradora Sopladora Portátil Inalámbrica Auto Y Hogar Usb", "seller": null, "price": "130.900", "reviews_rating_number": "5.0", "reviews_amount": "(6)"},
{"name": "Kit Mini Aspiradora & Sopladora Aire Limpieza Alta Velocidad", "seller": null, "price": "55.835", "reviews_rating_number": "5.0", "reviews_amount": "(2)"},
{"name": "Aspiradora Trent Vc19k Seco - Mojado Multifuncional 1200W 10l Filtro De Tela Y Función Soplado", "seller": "Por TRENT ", "price": "139.900", "reviews_rating_number": "4.6", "reviews_amount": "(1231)"},
{"name": "Aspiradora Industrial Pektra 15 Litros Polvo Liquido Acero Inoxidable", "seller": "Por Pektra ", "price": "199.999", "reviews_rating_number": "4.6", "reviews_amount": "(3909)"},
{"name": "Atma Aspiradora Dual Force Power Polvo Y Liquidos As9221pi Color Gris/Violeta", "seller": null, "price": "199.999", "reviews_rating_number": "4.6", "reviews_amount": "(1515)"},
{"name": "Aspiradora Trapeadora Robot Gadnic Clean Duo Z900 Negra", "seller": "Por Gadnic ", "price": "379.999", "reviews_rating_number": "4.7", "reviews_amount": "(2025)"},
{"name": "Combo Hidrolavadora Luxus 1400w + Aspiradora Luxus 1000w Color Negro Frecuencia 50", "seller": "Por Luxus ", "price": "321.674", "reviews_rating_number": "4.8", "reviews_amount": "(39)"},
{"name": "Aspiradora De Mano Vertical 2 En 1 Daewoo Color Blanco Moppy DVC-105 con accesorios", "seller": null, "price": "102.850", "reviews_rating_number": "4.5", "reviews_amount": "(2640)"},
{"name": "Aspiradora Gadnic Vc13 1L 110w inalámbrica 2 en 1 Recargable Indicador LED Batería 2000mAh", "seller": "Por Bidcom ", "price": "149.999", "reviews_rating_number": "4.4", "reviews_amount": "(282)"},
{"name": "Aspiradora Yelmo Para Automovil Azul As-3239", "seller": "Por GRAMABI ", "price": "39.300", "reviews_rating_number": "4.4", "reviews_amount": "(822)"},
{"name": "Yelmo aspiradora robot As-7070 inteligente mopa azul", "seller": null, "price": "239.999", "reviews_rating_number": "4.3", "reviews_amount": "(1978)"},
{"name": "Combo Hidrolavadora Alta Presion 110 Bar 1400w Autostop Dogo + Aspiradora Tacho Acero Inoxidable 15 Lts 1200w Con Filtro Hepa Para Polvo Liquido Versa", "seller": "Por Pideweb ", "price": "270.686", "reviews_rating_number": "5.0", "reviews_amount": "(40)"},
{"name": "Aspiradora Inalámbrica Atma 2 En 1 Dual Force Power As7922pi", "seller": null, "price": "155.979", "reviews_rating_number": "4.5", "reviews_amount": "(2519)"},
{"name": "Aspiradora Para Autos Vehiculos Asientos Sillas Bebes", "seller": "Por Newtek ", "price": "24.999", "reviews_rating_number": "4.2", "reviews_amount": "(211)"},
{"name": "Aspiradora Inalámbrica 2 En 1 Aspira Seco-húmedo 2000mah Westinghouse Wfvckt31", "seller": null, "price": "134.999", "reviews_rating_number": "4.6", "reviews_amount": "(16)"},
{"name": "Aspiradora Robot Atma Atar21c1pi - Trapeadora - Anti-choque Color Blanco", "seller": "Por SEVERANCE ", "price": "238.499", "reviews_rating_number": "4.3", "reviews_amount": "(303)"},
{"name": "Combo Aspiradora Industrial 10l 1000w Hidrolavadora Kommberg Amarillo 50hz", "seller": "Por KOMMBERG ", "price": "214.353", "reviews_rating_number": "4.7", "reviews_amount": "(126)"},
{"name": "Yelmo As-3240 Aspiradora Para Auto Recargable Usb Color Gris", "seller": null, "price": "59.899", "reviews_rating_number": "4.4", "reviews_amount": "(13143)"},
{"name": "Aspiradora de mano para Auto 120W JD Car Force Seco y Húmedo Filtro Hepa Color Negro", "seller": "Por JD ", "price": "47.999", "reviews_rating_number": "4.3", "reviews_amount": "(72)"},
{"name": "Aspiradora inalambrica Samsung Jet 60 cyclone inverter", "seller": "Por Isern Hogar ", "price": "562.258", "reviews_rating_number": "4.6", "reviews_amount": "(107)"},
{"name": "Aspiradora Robot Smart Alexa Bateria 4930mah Blanca Ezviz", "seller": "Por Tecnofast ", "price": "555.000", "reviews_rating_number": "4.7", "reviews_amount": "(221)"},
{"name": "Combo Aspiradora Industrial Inox Hidrolavadora Kommberg Amarillo 50hz", "seller": "Por EKKON EXPERTOS ", "price": "236.000", "reviews_rating_number": "4.8", "reviews_amount": "(49)"},
{"name": "Aspiradora Suono de tacho para el hogar o la oficina 15 l acero inox 1300w color plateado", "seller": "Por Mercado Libre ", "price": "79.999", "reviews_rating_number": "4.6", "reviews_amount": "(765)"},
{"name": "Aspiradora Para Auto Gadnic 80W Portatil Negro Potente", "seller": "Por Bidcom ", "price": "44.099", "reviews_rating_number": "4.1", "reviews_amount": "(459)"},
{"name": "Aspiradora Limpia Tapizado Y Alfombra Portátil Kommberg De Tacho 500w 1.5l Kb-lat500", "seller": "Por KOMMBERG ", "price": "159.890", "reviews_rating_number": "4.6", "reviews_amount": "(35)"},
{"name": "Aspiradora robot Ultracomb As-6061 color antracita/negro", "seller": null, "price": "134.986", "reviews_rating_number": "4.3", "reviews_amount": "(1154)"},
{"name": "Combo Hidrolavadora Alta Presion 110 Bar 1400w Autostop Dogo + Aspiradora Tacho 10 Lts 1000w Con Bolsa Lavable Para Polvo Liquido Daewoo", "seller": "Por Pideweb ", "price": "264.373", "reviews_rating_number": "4.6", "reviews_amount": "(26)"},
{"name": "Aspiradora Gadnic 700w Limpia Tapizado Con Accesorios Color Blanco", "seller": "Por Bidcom ", "price": "230.499", "reviews_rating_number": "4.3", "reviews_amount": "(4)"},
{"name": "Aspiradora de Mano 12v Para Auto Portátil 108w Filtro HEPA Cable 45Mts", "seller": "Por Bidcom ", "price": "39.999", "reviews_rating_number": "4.3", "reviews_amount": "(1888)"},
{"name": "Aspiradora Sopladora Shopvac De Tacho Polvo/liquido 20L 1800 W Acero Inox/Plateado Apta Uso Profesional Portatil", "seller": "Por Tecnofast ", "price": "249.990", "reviews_rating_number": "4.7", "reviews_amount": "(113)"},
{"name": "Aspiradora Trapeadora Robot Atma Atar21c1dh Blanca", "seller": "Por SEVERANCE ", "price": "309.999", "reviews_rating_number": "4.4", "reviews_amount": "(664)"},
{"name": "Combo Hidrolavadora Kommberg + Aspiradora Industrial Rojo", "seller": "Por KOMMBERG ", "price": "239.890", "reviews_rating_number": "4.5", "reviews_amount": "(8)"},
{"name": "Aspiradora Yelmo As3323 Agua Y Polvo 1400w 23 Lts Color Verde/Gris", "seller": "Por AJAXGOLD ", "price": "86.950", "reviews_rating_number": "4.7", "reviews_amount": "(4285)"},
{"name": "Aspiradora De Mano Inalambrica Para Coche Oficinas Y Hogar", "seller": null, "price": "30.000", "reviews_rating_number": "3.5", "reviews_amount": "(13)"},
{"name": "Aspiradora Trineo Atma Compact Power As8913pi 1.5l 1500w Color Bordó", "seller": "Por Trendy deals ", "price": "107.699", "reviews_rating_number": "4.8", "reviews_amount": "(110)"},
{"name": "Aspiradora Robot Gadnic 3 Modos Limpieza Poder De Succión Negro", "seller": null, "price": "299.999", "reviews_rating_number": "4.5", "reviews_amount": "(651)"},
{"name": "Aspiradora Multifuncion Kärcher Wdl 1s", "seller": "Por Mercado Libre ", "price": "120.000", "reviews_rating_number": "4.7", "reviews_amount": "(510)"},
{"name": "Aspiradora Auto Recargable Portátil 94w Pektra + Accesorios Rojo", "seller": "Por Hidroal ", "price": "89.999", "reviews_rating_number": "4.2", "reviews_amount": "(95)"},
{"name": "Aspiradora Inalambrica Plegable De Mano Peugeot Nantes 3 en 1 400w 3 Velocidades Color Negro", "seller": "Por PEUGEOT Smart Living ", "price": "429.999", "reviews_rating_number": "4.5", "reviews_amount": "(72)"},
{"name": "Aspiradora robot Xiaomi Vacuum S20 blanca", "seller": null, "price": "536.000", "reviews_rating_number": "4.7", "reviews_amount": "(400)"},
{"name": "Aspiradora Sin Bolsa Kärcher Vcl 1", "seller": "Por Mercado Libre ", "price": "70.000", "reviews_rating_number": "4.7", "reviews_amount": "(2021)"},
{"name": "Aspiradora Sopladora Portátil Inalámbrica Auto Y Hogar Usb", "seller": null, "price": "130.900", "reviews_rating_number": "5.0", "reviews_amount": "(6)"},
{"name": "Aspiradora De Mano Inalámbrica Gadnic 80W Multiuso 4 En 1", "seller": "Por Bidcom ", "price": "71.299", "reviews_rating_number": "4.0", "reviews_amount": "(163)"},
{"name": "Aspiradora Vertical Gadnic JT60Y 2 En 1 Multifunción Deposito 1 Litro Color Negro", "seller": "Por Bidcom ", "price": "79.999", "reviews_rating_number": "4.7", "reviews_amount": "(466)"},
{"name": "Lava aspiradora industrial De tacho Elsea Powerclean RC230P 23L roja, gris y negra 50Hz/60Hz", "seller": "Por GRAMMATICA ", "price": "749.990", "reviews_rating_number": "4.8", "reviews_amount": "(159)"},
{"name": "Aspiradora La958 Chromepower Liliana", "seller": null, "price": "158.999", "reviews_rating_number": "4.5", "reviews_amount": "(61)"},
{"name": "Aspiradora Vertical Electrolux STKs VERTICAIS STK12 1.2L negra 50Hz/60Hz 3015AKBR401", "seller": "Por Electrolux ", "price": "65.685", "reviews_rating_number": "4.7", "reviews_amount": "(473)"},
{"name": "Aspiradora De Mano Vertical 2 En 1 600w Belarra Ah600", "seller": "Por Belarra ", "price": "169.009", "reviews_rating_number": "4.6", "reviews_amount": "(306)"},
{"name": "Kommberg KB-VC60LG 60L aspiradora y sopladora profesional 2800w", "seller": "Por EKKON EXPERTOS ", "price": "459.890", "reviews_rating_number": "4.6", "reviews_amount": "(48)"},
{"name": "Aspiradora Liliana - La950", "seller": "Por PETENATTI HOGAR ", "price": "91.277", "reviews_rating_number": "4.7", "reviews_amount": "(2049)"},
{"name": "Aspiradora De tacho Kommberg KB-VC1400 15L 50Hz/60Hz", "seller": "Por KOMMBERG ", "price": "101.059", "reviews_rating_number": "4.7", "reviews_amount": "(520)"},
{"name": "Aspiradora Sopladora Stanley 15 Lts 1300Watts Aspira Polvo y Liquido Sl1901-4b", "seller": "Por FASTSTORE ", "price": "117.645", "reviews_rating_number": "4.7", "reviews_amount": "(943)"},
{"name": "Aspiradora De Tacho Gadnic Alta Potencia Gran Capacidad Color Gris oscuro", "seller": "Por Bidcom ", "price": "122.699", "reviews_rating_number": "4.6", "reviews_amount": "(38)"},
{"name": "Aspiradora Yelmo As-3244 395ml Limpieza Del Hogar Celeste/naranja", "seller": "Por Yelmo ", "price": "125.004", "reviews_rating_number": "4.5", "reviews_amount": "(2)"},
{"name": "Aspiradora Gadnic De Tacho Alto Rendimiento Doméstico 20 Litros 1200W", "seller": "Por Gadnic ", "price": "159.599", "reviews_rating_number": "4.6", "reviews_amount": "(42)"},
{"name": "Aspiradora de Tacho Gadnic 15L Silenciosa Sopladora 1200W", "seller": "Por Gadnic ", "price": "187.849", "reviews_rating_number": "4.6", "reviews_amount": "(98)"},
{"name": "Aspiradora Ultracomb As-4220 Sin Bolsa 1600w Filtro Hepa Ep", "seller": "Por Distribuidora MAYA ", "price": "99.999", "reviews_rating_number": null, "reviews_amount": null},
{"name": "Aspiradora Ultracomb As4224 1800w Sin Bolsa 2.5l Filtro Hepa", "seller": "Por IOW Insumos Odontologicos Web ", "price": "105.999", "reviews_rating_number": "4.7", "reviews_amount": "(92)"},
{"name": "Aspiradora Recargable Yelmo As-3244 Usb Luz Led Filtro H.e.p.a Turquesa", "seller": null, "price": "99.999", "reviews_rating_number": "4.4", "reviews_amount": "(158)"},
{"name": "Aspiradora Recargable Yelmo As-3244 Usb Led Filtro H.e.p.a Turquesa", "seller": null, "price": "54.000", "reviews_rating_number": null, "reviews_amount": null},
{"name": "Aspiradora Ultracomb As4224 1800w Sin Bolsa 2.5l Filtro Hepa", "seller": "Por IOW Insumos Odontologicos Web ", "price": "145.799", "reviews_rating_number": "4.0", "reviews_amount": "(3)"},
{"name": "Aspiradora Recargable Yelmo As-3244 Usb Luz Led Filtro He.pa", "seller": null, "price": "45.299", "reviews_rating_number": null, "reviews_amount": null},
{"name": "Aspiradora Recargable Yelmo As-3244 Usb Luz Led Filtro Hep Celeste/naranja", "seller": null, "price": "125.004", "reviews_rating_number": null, "reviews_amount": null},
{"name": "Aspiradora Yelmo As3224 1600w Filtro Hepa Rosa Rosa Chicle", "seller": "Por Tidi ", "price": "180.499", "reviews_rating_number": null, "reviews_amount": null},
{"name": "Aspiradora Gadnic Sopladora 20 Lts Multifunción 13 Kpa Plateado", "seller": "Por Bidcom ", "price": "130.699", "reviews_rating_number": null, "reviews_amount": null},
{"name": "Aspiradora Ultracomb As-4220 Sin Bolsa 1600w Filtro Hepa Gris/naranja", "seller": null, "price": "99.000", "reviews_rating_number": null, "reviews_amount": null},
{"name": "Aspiradora Recargable Yelmo As-3244 Usb Luz Led Filtro Hepa", "seller": "Por IOW Insumos Odontologicos Web ", "price": "80.000", "reviews_rating_number": null, "reviews_amount": null},
{"name": "Aspiradora Recargable Yelmo As-3244 Usb Luz Led Filtro Lh", "seller": "Por LHCONFORT ", "price": "95.999", "reviews_rating_number": null, "reviews_amount": null},
{"name": "Aspiradora Ultracomb As-4220 Sin Bolsa 1600w Filtro Hepa", "seller": null, "price": "123.573", "reviews_rating_number": null, "reviews_amount": null},
{"name": "Aspiradora Ultracomb As-4220 Sin Bolsa 1600w Filtro Hepa Ep ", "seller": "Por Tecnocenter ", "price": "84.500", "reviews_rating_number": "4.3", "reviews_amount": "(3)"},
{"name": "Aspiradora Ultracomb As-4220 Sin Bolsa 1600w Filtro Hepa Ep", "seller": null, "price": "145.000", "reviews_rating_number": null, "reviews_amount": null},
{"name": "Aspiradora Portatil Vexo 80w 12v Filtro Hepa + Accesorios Repuestos Floresta", "seller": "Por REPUESTOS FLORESTA ", "price": "22.000", "reviews_rating_number": null, "reviews_amount": null},
{"name": "Aspiradora De Tacho Gadnic Alta Potencia Gran Capacidad Color Gris oscuro", "seller": "Por Bidcom ", "price": "122.699", "reviews_rating_number": "4.6", "reviews_amount": "(38)"},
{"name": "Aspiradora Yelmo As-3244 395ml Limpieza Del Hogar Celeste/naranja", "seller": "Por Yelmo ", "price": "108.699", "reviews_rating_number": "4.5", "reviews_amount": "(2)"},
{"name": "Aspiradora Yelmo As3224 Sin Bolsa 1600w. 2 Lts Filtro Hepa  Rosa/gris", "seller": "Por SERVICE BAIRES ", "price": "183.038", "reviews_rating_number": null, "reviews_amount": null},
{"name": "Aspiradora Yelmo As 3230 68db Sin Bolsa Trineo", "seller": null, "price": "219.818", "reviews_rating_number": null, "reviews_amount": null},
{"name": "Aspiradora Recargable Yelmo As-3244 Usb Luz Led Filtro Hepa", "seller": "Por IOW Insumos Odontologicos Web ", "price": "80.000", "reviews_rating_number": null, "reviews_amount": null},
{"name": "Aspiradora Yelmo As3228 2000w 3,5lts Sin Bolsa Filtro Hepa Color Rosa", "seller": null, "price": "159.999", "reviews_rating_number": "4.8", "reviews_amount": "(1274)"},
{"name": "Aspiradora Recargable Yelmo As-3244 Usb Luz Led Filtro H.e.p.a Turquesa", "seller": null, "price": "99.999", "reviews_rating_number": "4.4", "reviews_amount": "(158)"},
{"name": "Aspiradora Yelmo As-3228 Trineo 50hz", "seller": "Por IOW Insumos Odontologicos Web ", "price": "284.434", "reviews_rating_number": "4.8", "reviews_amount": "(1274)"},
{"name": "Yelmo As3323 Aspiradora Tambor Plastico Agua Polvo 23l 1400w", "seller": null, "price": "119.999", "reviews_rating_number": "4.5", "reviews_amount": "(50)"},
{"name": "Aspiradora Yelmo As3323 Agua Y Polvo 1400w 23l Color Verde Verde/gris", "seller": "Por Yelmo ", "price": "213.784", "reviews_rating_number": "4.3", "reviews_amount": "(6)"},
{"name": "Aspiradora Recargable Yelmo As-3244 Usb Luz Led Filtro He.pa", "seller": null, "price": "45.299", "reviews_rating_number": null, "reviews_amount": null},
{"name": "Aspiradora Recargable Yelmo As-3244 Usb Luz Led Filtro Hep Celeste/naranja", "seller": null, "price": "125.004", "reviews_rating_number": null, "reviews_amount": null},
{"name": "Aspiradora Fema 1400w 60 Litros Polvo Líquidos", "seller": null, "price": "414.950", "reviews_rating_number": null, "reviews_amount": null},
{"name": "Aspiradora Yelmo As3323 Agua Y Polvo 1400w 23l Color Verde Verde/gris", "seller": "Por Yelmo ", "price": "213.784", "reviews_rating_number": null, "reviews_amount": null},
{"name": "Aspiradora Yelmo As3224 1600w Filtro Hepa Rosa Rosa Chicle", "seller": "Por Tidi ", "price": "180.499", "reviews_rating_number": null, "reviews_amount": null},
{"name": "Aspiradora Yelmo 2000w 3.5 Lts As-3228 Sin Bolsa Filtro Hepa", "seller": "Por Electro Point ", "price": "116.299", "reviews_rating_number": "4.7", "reviews_amount": "(75)"},
{"name": "Aspiradora Yelmo Sin Bolsa As-3224 1600w  2lts Filtro Hepa", "seller": "Por Electro Point ", "price": "100.979", "reviews_rating_number": "4.6", "reviews_amount": "(46)"},
{"name": "Yelmo As-3240 Aspiradora Recargable Usb Gris 395 Ml Gris", "seller": "Por Yelmo ", "price": "88.894", "reviews_rating_number": null, "reviews_amount": null},
{"name": "Aspiradora Marca Yelmo Modelo As-3210 Verde/gris", "seller": "Por Yelmo ", "price": "155.499", "reviews_rating_number": "4.5", "reviews_amount": "(4)"},
{"name": "Aspiradora Yelmo Agua Y Polvo 1400w 23 Lts", "seller": null, "price": "188.363", "reviews_rating_number": "5.0", "reviews_amount": "(1)"},
{"name": "Aspiradora C/bolsa Yelmo Canister As-3210 1100w ", "seller": null, "price": "142.550", "reviews_rating_number": null, "reviews_amount": null},
{"name": "Aspiradora Sin Bolsa Yelmo As-3228 3.5l 2000w Filtro Hepa", "seller": null, "price": "223.999", "reviews_rating_number": "5.0", "reviews_amount": "(1)"},
{"name": "Aspiradora Yelmo As-3224 1600w Filtro Hepa Azul", "seller": null, "price": "200.750", "reviews_rating_number": null, "reviews_amount": null},
{"name": "Aspiradora Yelmo As-3224 1600w Filtro Hepa Azul", "seller": null, "price": "192.850", "reviews_rating_number": "4.0", "reviews_amount": "(1)"},
{"name": "Aspiradora Yelmo As-3228 2000w Filtro Hepa Gris Rosa", "seller": null, "price": "332.650", "reviews_rating_number": null, "reviews_amount": null},
{"name": "Aspiradora Yelmo As-3228 2000w Filtro Hepa Gris Rosa", "seller": null, "price": "302.399", "reviews_rating_number": null, "reviews_amount": null},
{"name": "Aspiradora Yelmo As-3228 2000w Filtro Hepa Gris Rosa", "seller": null, "price": "297.975", "reviews_rating_number": null, "reviews_amount": null},
{"name": "Aspiradora Yelmo As-3244 395ml Limpieza Del Hogar Celeste/naranja", "seller": "Por Yelmo ", "price": "125.004", "reviews_rating_number": "4.5", "reviews_amount": "(2)"},
{"name": "Aspiradora Recargable Yelmo As-3244 Usb Luz Led Filtro Hepa", "seller": "Por IOW Insumos Odontologicos Web ", "price": "80.000", "reviews_rating_number": null, "reviews_amount": null},
{"name": "Aspiradora Recargable Yelmo As-3244 Usb Luz Led Filtro H.e.p.a Turquesa", "seller": null, "price": "99.999", "reviews_rating_number": "4.4", "reviews_amount": "(158)"},
{"name": "Aspiradora De Tacho Gadnic Alta Potencia Gran Capacidad Color Gris oscuro", "seller": "Por Bidcom ", "price": "122.699", "reviews_rating_number": "4.6", "reviews_amount": "(38)"},
{"name": "Aspiradora Trineo Spica Sp-1200 Bolsa De Tela Cepillo 1200w Cable Retractil Niveles Color Azul", "seller": "Por Spica ", "price": "130.699", "reviews_rating_number": "4.2", "reviews_amount": "(57)"},
{"name": "Aspiradora Yelmo As 3224 2lts Filtro S/bolsa Hepa 1600w 220v Gris/azul", "seller": "Por GRAMABI ", "price": "187.400", "reviews_rating_number": null, "reviews_amount": null},
{"name": "Aspiradora Yelmo As3323 Agua Y Polvo 1400w 23l Color Verde Verde/gris", "seller": "Por Yelmo ", "price": "213.784", "reviews_rating_number": "4.3", "reviews_amount": "(6)"},
{"name": "Aspiradora Yelmo As3224 Sin Bolsa 1600w. 2 Lts Filtro Hepa  Rosa/gris", "seller": "Por SERVICE BAIRES ", "price": "183.038", "reviews_rating_number": null, "reviews_amount": null},
{"name": "Aspiradora Yelmo As-3239 12v Azul 395 Ml 80w 12 Volts", "seller": null, "price": "101.021", "reviews_rating_number": null, "reviews_amount": null},
{"name": "Aspiradora Yelmo As-3240 Recargable De Mano 80w Usb", "seller": null, "price": "42.999", "reviews_rating_number": null, "reviews_amount": null},
{"name": "Aspiradora Recargable Yelmo As-3244 Usb Luz Led Filtro Hepa", "seller": "Por IOW Insumos Odontologicos Web ", "price": "58.500", "reviews_rating_number": null, "reviews_amount": null},
{"name": "Aspiradora Recargable Yelmo As-3244 Usb Led Filtro H.e.p.a Turquesa", "seller": null, "price": "54.000", "reviews_rating_number": null, "reviews_amount": null},
{"name": "Aspiradora Recargable Yelmo As-3244 Usb Luz Led Filtro He.pa", "seller": null, "price": "45.299", "reviews_rating_number": null, "reviews_amount": null},
{"name": "Aspiradora Recargable Yelmo As-3244 Usb Luz Led Filtro Hep Celeste/naranja", "seller": null, "price": "125.004", "reviews_rating_number": null, "reviews_amount": null},
{"name": "Aspiradora Yelmo As3323 Agua Y Polvo 1400w 23l Color Verde Verde/gris", "seller": "Por Yelmo ", "price": "213.784", "reviews_rating_number": null, "reviews_amount": null},
{"name": "Aspiradora Trineo Spica Sp-1200 Bolsa De Tela 1200w 220v Azul", "seller": "Por LIBERCAM ", "price": "119.999", "reviews_rating_number": "4.0", "reviews_amount": "(9)"},
{"name": "Aspiradora Recargable Yelmo As-3244 Usb Luz Led Filtro Lh", "seller": "Por LHCONFORT ", "price": "95.999", "reviews_rating_number": null, "reviews_amount": null},
{"name": "Aspiradora Yelmo Agua Y Polvo 1400w 23 Lts", "seller": null, "price": "188.363", "reviews_rating_number": "5.0", "reviews_amount": "(1)"},
{"name": "Aspiradora Yelmo As3323 Agua Y Polvo 1400w 23 Lts Color Verd", "seller": "Por Grupo Marquez ", "price": "114.199", "reviews_rating_number": "4.0", "reviews_amount": "(1)"},
{"name": "Aspiradora Yelmo As3323 Agua Y Polvo 1400w - Aj Hogar ", "seller": null, "price": "126.400", "reviews_rating_number": "5.0", "reviews_amount": "(1)"},
{"name": "Aspiradora Yelmo As-3224 1600w Filtro Hepa Azul", "seller": null, "price": "174.999", "reviews_rating_number": null, "reviews_amount": null},
{"name": "Aspiradora Gadnic De Tacho Alto Rendimiento Doméstico 20 Litros 1200W", "seller": "Por Gadnic ", "price": "159.599", "reviews_rating_number": "4.6", "reviews_amount": "(42)"},
{"name": "Aspiradora De Tacho Gadnic Alta Potencia Gran Capacidad Color Gris oscuro", "seller": "Por Bidcom ", "price": "122.699", "reviews_rating_number": "4.6", "reviews_amount": "(38)"},
{"name": "Aspiradora Yelmo As3228 2000w 3,5lts Sin Bolsa Filtro Hepa Color Rosa", "seller": null, "price": "159.999", "reviews_rating_number": "4.8", "reviews_amount": "(1274)"},
{"name": "Aspiradora Yelmo As-3228 Trineo 50hz", "seller": "Por IOW Insumos Odontologicos Web ", "price": "284.434", "reviews_rating_number": "4.8", "reviews_amount": "(1274)"},
{"name": "Aspiradora Yelmo As 3224 2lts Filtro S/bolsa Hepa 1600w Color Gris/Azul", "seller": null, "price": "149.999", "reviews_rating_number": "4.7", "reviews_amount": "(779)"},
{"name": "Aspiradora industrial De tacho Goodyear GY-ZN-1201-12L 12L amarilla y negra 50Hz", "seller": null, "price": "204.855", "reviews_rating_number": "4.1", "reviews_amount": "(27)"},
{"name": "Aspiradora Industrial Profesional Gadnic De Tacho 18l 1200w", "seller": "Por Gadnic ", "price": "119.999", "reviews_rating_number": "3.3", "reviews_amount": "(3)"},
{"name": "Aspiradora Yelmo As3224 1600w Filtro Hepa Rosa Rosa Chicle", "seller": "Por Tidi ", "price": "180.499", "reviews_rating_number": null, "reviews_amount": null},
{"name": "Aspiradora Gadnic Sopladora 20 Lts Multifunción 13 Kpa Plateado", "seller": "Por Bidcom ", "price": "130.699", "reviews_rating_number": null, "reviews_amount": null},
{"name": "Aspiradora Yelmo 2000w 3.5 Lts As-3228 Sin Bolsa Filtro Hepa", "seller": "Por Electro Point ", "price": "116.299", "reviews_rating_number": "4.7", "reviews_amount": "(75)"},
{"name": "Aspiradora Yelmo As3224 Sin Bolsa 1600w. 2 Lts Filtro Hepa  Rosa/gris", "seller": "Por SERVICE BAIRES ", "price": "183.038", "reviews_rating_number": null, "reviews_amount": null},
{"name": "Yelmo As-3240 Aspiradora Recargable Usb Gris 395 Ml Gris", "seller": "Por Yelmo ", "price": "88.894", "reviews_rating_number": null, "reviews_amount": null},
{"name": "Aspiradora Recargable Yelmo As-3244 Usb Luz Led Filtro Hepa", "seller": "Por IOW Insumos Odontologicos Web ", "price": "80.000", "reviews_rating_number": null, "reviews_amount": null},
{"name": "Aspiradora Yelmo As 3224 2lts Filtro S/bolsa Hepa 1600w", "seller": null, "price": "158.008", "reviews_rating_number": null, "reviews_amount": null},
{"name": "Aspiradora Sin Bolsa Yelmo As-3228 3.5l 2000w Filtro Hepa", "seller": null, "price": "223.999", "reviews_rating_number": "5.0", "reviews_amount": "(1)"},
{"name": "Aspiradora Yelmo As-3224 1600w Filtro Hepa Azul", "seller": null, "price": "200.750", "reviews_rating_number": null, "reviews_amount": null},
{"name": "Aspiradora Yelmo As-3224 1600w Filtro Hepa Azul", "seller": null, "price": "192.850", "reviews_rating_number": "4.0", "reviews_amount": "(1)"},
{"name": "Aspiradora Yelmo As-3228 2000w Filtro Hepa Gris Rosa", "seller": null, "price": "332.650", "reviews_rating_number": null, "reviews_amount": null},
{"name": "Aspiradora Yelmo As-3224 1600w Filtro Hepa Azul", "seller": null, "price": "174.999", "reviews_rating_number": null, "reviews_amount": null},
{"name": "Aspiradora Yelmo As-3224 1600w Filtro Hepa Azul", "seller": null, "price": "199.999", "reviews_rating_number": null, "reviews_amount": null},
{"name": "Aspiradora Yelmo As-3228 2000w Filtro Hepa Gris Rosa", "seller": null, "price": "347.750", "reviews_rating_number": null, "reviews_amount": null},
{"name": "Aspiradora Yelmo As-3228 2000w Filtro Hepa Gris Rosa", "seller": null, "price": "297.975", "reviews_rating_number": null, "reviews_amount": null},
{"name": "Aspiradora Recargable Yelmo As-3244 Usb Luz Led Filtro He.pa", "seller": null, "price": "45.299", "reviews_rating_number": null, "reviews_amount": null},
{"name": "Aspiradora Recargable Yelmo As-3244 Usb Luz Led Filtro Hep Celeste/naranja", "seller": null, "price": "125.004", "reviews_rating_number": null, "reviews_amount": null},
{"name": "Aspiradora Yelmo As-3244 395ml Limpieza Del Hogar Celeste/naranja", "seller": "Por Yelmo ", "price": "125.004", "reviews_rating_number": "4.5", "reviews_amount": "(2)"},
{"name": "Yelmo As-3240 Aspiradora Para Auto Recargable Usb Color Gris", "seller": null, "price": "59.899", "reviews_rating_number": "4.4", "reviews_amount": "(13143)"},
{"name": "Aspiradora Eléctrica Trineo 1400w Bolsa Cepillo Multifunción", "seller": "Por TUATIENDA ONLINE ", "price": "85.713", "reviews_rating_number": null, "reviews_amount": null},
{"name": "Aspiradora Recargable Yelmo As-3244 Usb Luz Led Filtro H.e.p.a Turquesa", "seller": null, "price": "99.999", "reviews_rating_number": "4.4", "reviews_amount": "(158)"},
{"name": "Mini Aspirador 3/1 Aspira Modelo As-228 Recargable Por Usb", "seller": "Por MIPONG ", "price": "9.499", "reviews_rating_number": null, "reviews_amount": null},
{"name": "Aspiradora Para Auto Y Hogar Yelmo As-3240 Recargable Usb C", "seller": null, "price": "40.799", "reviews_rating_number": "4.1", "reviews_amount": "(7)"},
{"name": "Aspiradora Recargable Yelmo As-3244 Usb Led Filtro H.e.p.a Turquesa", "seller": null, "price": "54.000", "reviews_rating_number": null, "reviews_amount": null},
{"name": "Mini Aspirador 3/1 Aspira Modelo As-228 Recargable Por Usb", "seller": null, "price": "9.499", "reviews_rating_number": null, "reviews_amount": null},
{"name": "Aspiradora Para Auto Y Hogar Yelmo As-3240 Recargable Usb", "seller": null, "price": "49.000", "reviews_rating_number": "4.3", "reviews_amount": "(4)"},
{"name": "Aspiradora Fema 1400w 60 Litros Polvo Líquidos", "seller": null, "price": "414.950", "reviews_rating_number": null, "reviews_amount": null},
{"name": "Aspiradora Trineo Spica Sp-1200 Bolsa De Tela 1200w 220v Azul", "seller": "Por LIBERCAM ", "price": "119.999", "reviews_rating_number": "4.0", "reviews_amount": "(9)"},
{"name": "Aspiradora Electrica 2400w 60 Lts Dyllu By Total", "seller": "Por LUXONO ", "price": "608.387", "reviews_rating_number": null, "reviews_amount": null},
{"name": "Aspiradora Húmedo/seco 60 Lts Jadever Jdvr5a60-4 2400w", "seller": "Por Tecnofast ", "price": "740.990", "reviews_rating_number": null, "reviews_amount": null},
{"name": "Aspiradora Industrial Tacho 50l 1400w Lusqtoff La-5001m", "seller": "Por MISTERMAQ ", "price": "381.799", "reviews_rating_number": null, "reviews_amount": null},
{"name": "Yelmo As-3240 Aspiradora Recargable Usb Gris 395 Ml Gris", "seller": "Por Yelmo ", "price": "88.894", "reviews_rating_number": null, "reviews_amount": null},
{"name": "Aspiradora Recargable Yelmo As-3244 Usb Luz Led Filtro Hepa", "seller": "Por IOW Insumos Odontologicos Web ", "price": "80.000", "reviews_rating_number": null, "reviews_amount": null},
{"name": "Aspiradora Yelmo As3323 Agua Y Polvo 1400w - Aj Hogar ", "seller": null, "price": "126.400", "reviews_rating_number": "5.0", "reviews_amount": "(1)"},
{"name": "Aspiradora De Tacho 20lts 1300w Dinax", "seller": null, "price": "93.999", "reviews_rating_number": null, "reviews_amount": null},
{"name": "Aspiradora Electrica 2400w 60 Lts Dyllu By Total Turquesa", "seller": "Por LUXONO ", "price": "548.470", "reviews_rating_number": null, "reviews_amount": null},
{"name": "Aspiradora Trineo Spica Sp-1200 Bolsa De Tela 1200w 220v Azul", "seller": "Por Spica ", "price": "130.699", "reviews_rating_number": "4.6", "reviews_amount": "(37)"},
{"name": "Aspiradora Húmedo/seco 60 Lts Jadever Jdvr5a60-4 2400w", "seller": "Por Tecnofast ", "price": "1.222.629", "reviews_rating_number": null, "reviews_amount": null},
{"name": "Aspiradora Recargable Yelmo As-3244 Usb Luz Led Filtro Lh", "seller": "Por LHCONFORT ", "price": "95.999", "reviews_rating_number": null, "reviews_amount": null},
{"name": "Aspiradora Para Auto Yelmo As3240 Recargable Usb Filtro Hepa Gris", "seller": "Por TIO MUSA ", "price": "41.999", "reviews_rating_number": null, "reviews_amount": null},
{"name": "Aspiradora Recargable Yelmo As-3240 Hogar Y Auto Usb - Hepa", "seller": "Por Grupo Marquez ", "price": "50.299", "reviews_rating_number": null, "reviews_amount": null},
{"name": "Aspiradora Yelmo As-3240 Recargable De Mano 80w Usb", "seller": null, "price": "42.999", "reviews_rating_number": null, "reviews_amount": null},
{"name": "Aspiradora Electrica 2400w 60lts Marca Dyllu Garantiza Total", "seller": null, "price": "352.619", "reviews_rating_number": null, "reviews_amount": null},
{"name": "Aspiradora De Mano Yelmo As-3240", "seller": null, "price": "49.113", "reviews_rating_number": "5.0", "reviews_amount": "(1)"},
{"name": "Aspiradora Yelmo As3228 2000w 3,5lts Sin Bolsa Filtro Hepa Color Rosa", "seller": null, "price": "159.999", "reviews_rating_number": "4.8", "reviews_amount": "(1274)"},
{"name": "Aspiradora Yelmo As-3244 395ml Limpieza Del Hogar Celeste/naranja", "seller": "Por Yelmo ", "price": "125.004", "reviews_rating_number": "4.5", "reviews_amount": "(2)"},
{"name": "Aspiradora Yelmo As-3228 Trineo 50hz", "seller": "Por IOW Insumos Odontologicos Web ", "price": "284.434", "reviews_rating_number": "4.8", "reviews_amount": "(1274)"},
{"name": "Aspiradora Recargable Yelmo As-3244 Usb Luz Led Filtro Hepa", "seller": "Por IOW Insumos Odontologicos Web ", "price": "80.000", "reviews_rating_number": null, "reviews_amount": null},
{"name": "Aspiradora Recargable Yelmo As-3244 Usb Luz Led Filtro H.e.p.a Turquesa", "seller": null, "price": "99.999", "reviews_rating_number": "4.4", "reviews_amount": "(158)"},
{"name": "Aspiradora Recargable Yelmo As-3244 Usb Led Filtro H.e.p.a Turquesa", "seller": null, "price": "54.000", "reviews_rating_number": null, "reviews_amount": null},
{"name": "Aspiradora Recargable Yelmo As-3244 Usb Luz Led Filtro He.pa", "seller": null, "price": "45.299", "reviews_rating_number": null, "reviews_amount": null},
{"name": "Aspiradora Recargable Yelmo As-3244 Usb Luz Led Filtro Hep Celeste/naranja", "seller": null, "price": "125.004", "reviews_rating_number": null, "reviews_amount": null},
{"name": "Aspiradora Yelmo As3224 1600w Filtro Hepa Rosa Rosa Chicle", "seller": "Por Tidi ", "price": "180.499", "reviews_rating_number": null, "reviews_amount": null},
{"name": "Aspiradora Recargable Yelmo As-3244 Usb Luz Led Filtro Hepa", "seller": "Por IOW Insumos Odontologicos Web ", "price": "58.500", "reviews_rating_number": null, "reviews_amount": null},
{"name": "Aspiradora Sin Bolsa Yelmo As-3228 3.5l 2000w Filtro Hepa", "seller": null, "price": "223.999", "reviews_rating_number": "5.0", "reviews_amount": "(1)"},
{"name": "Aspiradora Yelmo As-3228 2000w Filtro Hepa Gris Rosa Gris/rosa", "seller": null, "price": "304.575", "reviews_rating_number": null, "reviews_amount": null},
{"name": "Aspiradora Yelmo As-3228 2000w Filtro Hepa Gris Rosa", "seller": null, "price": "332.650", "reviews_rating_number": null, "reviews_amount": null},
{"name": "Aspiradora Yelmo As-3228 2000w Filtro Hepa Gris Rosa", "seller": null, "price": "302.399", "reviews_rating_number": null, "reviews_amount": null},
{"name": "Aspiradora Yelmo As-3228 2000w Filtro Hepa Gris Rosa", "seller": null, "price": "351.750", "reviews_rating_number": null, "reviews_amount": null},
{"name": "Aspiradora Yelmo As-3228 2000w Filtro Hepa Gris Rosa", "seller": null, "price": "282.875", "reviews_rating_number": null, "reviews_amount": null},
{"name": "Aspiradora Yelmo As-3228 2000w Filtro Hepa Gris Rosa", "seller": null, "price": "313.599", "reviews_rating_number": null, "reviews_amount": null},
{"name": "Aspiradora Yelmo As-3228 2000w Filtro Hepa Gris Rosa", "seller": null, "price": "255.999", "reviews_rating_number": null, "reviews_amount": null},
{"name": "Aspiradora Yelmo As-3228 2000w Filtro Hepa Gris Rosa", "seller": null, "price": "332.650", "reviews_rating_number": null, "reviews_amount": null},
{"name": "Aspiradora Yelmo As-3228 Filtro Hepa 3.5l Multi-ciclónica  Gris/rosa", "seller": null, "price": "230.399", "reviews_rating_number": null, "reviews_amount": null},
{"name": "Aspiradora Yelmo As-3228 2000w Filtro Hepa Gris Rosa", "seller": null, "price": "302.399", "reviews_rating_number": null, "reviews_amount": null},
{"name": "Aspiradora Yelmo As-3228 2000w Filtro Hepa Gris Rosa", "seller": null, "price": "347.750", "reviews_rating_number": null, "reviews_amount": null},
{"name": "Aspiradora Yelmo As-3228 2000w Filtro Hepa Gris Rosa", "seller": null, "price": "297.975", "reviews_rating_number": null, "reviews_amount": null},
{"name": "Aspiradora Yelmo As3323 Agua Y Polvo 1400w 23l Color Verde Verde/gris", "seller": "Por Yelmo ", "price": "213.784", "reviews_rating_number": "4.3", "reviews_amount": "(6)"},
{"name": "Aspiradora Yelmo As-3244 395ml Limpieza Del Hogar Celeste/naranja", "seller": "Por Yelmo ", "price": "125.004", "reviews_rating_number": "4.5", "reviews_amount": "(2)"},
{"name": "Aspiradora Yelmo As3323 Agua Y Polvo 1400w 23l Color Verde Verde/gris", "seller": "Por Yelmo ", "price": "213.784", "reviews_rating_number": null, "reviews_amount": null},
{"name": "Aspiradora Yelmo As3228 2000w 3,5lts Sin Bolsa Filtro Hepa Color Rosa", "seller": null, "price": "159.999", "reviews_rating_number": "4.8", "reviews_amount": "(1274)"},
{"name": "Aspiradora Yelmo As3323 Agua Y Polvo 1400w 23 Lts Color Verde/Gris", "seller": "Por AJAXGOLD ", "price": "86.950", "reviews_rating_number": "4.7", "reviews_amount": "(4285)"},
{"name": "Aspiradora Recargable Yelmo As-3244 Usb Luz Led Filtro He.pa", "seller": null, "price": "45.299", "reviews_rating_number": null, "reviews_amount": null},
{"name": "Aspiradora Yelmo As-3210 2.5l  Verde Y Gris 220v Verde/gris", "seller": "Por Yelmo ", "price": "178.824", "reviews_rating_number": "4.5", "reviews_amount": "(2)"},
{"name": "Aspiradora Yelmo As3224 1600w Filtro Hepa Rosa Rosa Chicle", "seller": "Por Tidi ", "price": "180.499", "reviews_rating_number": null, "reviews_amount": null},
{"name": "Aspiradora C/bolsa Yelmo Canister As-3210 1100w ", "seller": null, "price": "142.550", "reviews_rating_number": null, "reviews_amount": null},
{"name": "Aspiradora Yelmo As3323 Agua Y Polvo 1400w 23 Lts Color Verd", "seller": "Por Grupo Marquez ", "price": "114.199", "reviews_rating_number": "4.0", "reviews_amount": "(1)"},
{"name": "Aspiradora Sin Bolsa Yelmo As-3228 3.5l 2000w Filtro Hepa", "seller": null, "price": "223.999", "reviews_rating_number": "5.0", "reviews_amount": "(1)"},
{"name": "Aspiradora Yelmo As3323 Agua Y Polvo 1400w 23 Lts Verde Verde/gris", "seller": "Por TIO MUSA ", "price": "99.999", "reviews_rating_number": null, "reviews_amount": null},
{"name": "Aspiradora Yelmo As3323 Agua Y Polvo 1400w - Aj Hogar ", "seller": null, "price": "126.400", "reviews_rating_number": "5.0", "reviews_amount": "(1)"},
{"name": "Aspiradora Yelmo As-3228 2000w Filtro Hepa Gris Rosa", "seller": null, "price": "351.750", "reviews_rating_number": null, "reviews_amount": null},
{"name": "Aspiradora Yelmo As-3228 2000w Filtro Hepa Gris Rosa", "seller": null, "price": "282.875", "reviews_rating_number": null, "reviews_amount": null},
{"name": "Aspiradora Yelmo As-3228 2000w Filtro Hepa Gris Rosa", "seller": null, "price": "313.599", "reviews_rating_number": null, "reviews_amount": null},
{"name": "Aspiradora Yelmo As-3228 2000w Filtro Hepa Gris Rosa", "seller": null, "price": "255.999", "reviews_rating_number": null, "reviews_amount": null},
{"name": "Aspiradora Yelmo As-3228 2000w Filtro Hepa Gris Rosa", "seller": null, "price": "332.650", "reviews_rating_number": null, "reviews_amount": null},
{"name": "Aspiradora Yelmo As-3210 Verde Y Gris 220v 50hz Incl Bolsa", "seller": null, "price": "112.499", "reviews_rating_number": null, "reviews_amount": null},
{"name": "Aspiradora Yelmo As-3228 2000w Filtro Hepa Gris Rosa", "seller": null, "price": "302.399", "reviews_rating_number": null, "reviews_amount": null},
{"name": "Aspiradora De Tacho Gadnic Alta Potencia Gran Capacidad Color Gris oscuro", "seller": "Por Bidcom ", "price": "122.699", "reviews_rating_number": "4.6", "reviews_amount": "(38)"},
{"name": "Aspiradora Yelmo As-3244 395ml Limpieza Del Hogar Celeste/naranja", "seller": "Por Yelmo ", "price": "125.004", "reviews_rating_number": "4.5", "reviews_amount": "(2)"},
{"name": "Yelmo As-3240 Aspiradora Para Auto Recargable Usb Color Gris", "seller": null, "price": "59.899", "reviews_rating_number": "4.4", "reviews_amount": "(13143)"},
{"name": "Aspiradora Recargable Yelmo As-3244 Usb Luz Led Filtro H.e.p.a Turquesa", "seller": null, "price": "99.999", "reviews_rating_number": "4.4", "reviews_amount": "(158)"},
{"name": "Aspiradora Yelmo As3228 2000w 3,5lts Sin Bolsa Filtro Hepa Color Rosa", "seller": null, "price": "159.999", "reviews_rating_number": "4.8", "reviews_amount": "(1274)"},
{"name": "Aspiradora Tacho Acero Ultracomb As-4314 34l 220v 1400w Plata/negro", "seller": "Por GRAMABI ", "price": "315.300", "reviews_rating_number": null, "reviews_amount": null},
{"name": "Aspiradora Yelmo As-3228 Trineo 50hz", "seller": "Por IOW Insumos Odontologicos Web ", "price": "284.434", "reviews_rating_number": "4.8", "reviews_amount": "(1274)"},
{"name": "Aspiradora Recargable Yelmo As-3244 Usb Led Filtro H.e.p.a Turquesa", "seller": null, "price": "54.000", "reviews_rating_number": null, "reviews_amount": null},
{"name": "Aspiradora Recargable Yelmo As-3244 Usb Luz Led Filtro He.pa", "seller": null, "price": "45.299", "reviews_rating_number": null, "reviews_amount": null},
{"name": "Aspiradora Recargable Yelmo As-3244 Usb Luz Led Filtro Hep Celeste/naranja", "seller": null, "price": "125.004", "reviews_rating_number": null, "reviews_amount": null},
{"name": "Aspiradora Yelmo As-3240 Para Auto Recargable Usb Gris", "seller": null, "price": "43.998", "reviews_rating_number": null, "reviews_amount": null},
{"name": "Yelmo As-3240 Aspiradora Recargable Usb Gris 395 Ml Gris", "seller": "Por Yelmo ", "price": "88.894", "reviews_rating_number": null, "reviews_amount": null},
{"name": "Aspiradora Recargable Yelmo As-3244 Usb Luz Led Filtro Hepa", "seller": "Por IOW Insumos Odontologicos Web ", "price": "80.000", "reviews_rating_number": null, "reviews_amount": null},
{"name": "Aspiradora Sin Bolsa Yelmo As-3228 3.5l 2000w Filtro Hepa", "seller": null, "price": "223.999", "reviews_rating_number": "5.0", "reviews_amount": "(1)"},
{"name": "Aspiradora Yelmo As-3228 2000w Filtro Hepa Gris Rosa", "seller": null, "price": "297.975", "reviews_rating_number": null, "reviews_amount": null},
{"name": "Aspiradora Tacho Acero Ultracomb As-4314 34l 220v 1400w Plata/negro", "seller": "Por GRAMABI ", "price": "315.300", "reviews_rating_number": null, "reviews_amount": null},
{"name": "Aspiradora Ultracomb As4220 Filtro Hepa 1,2 Litros 1600w", "seller": "Por IOW Insumos Odontologicos Web ", "price": "83.000", "reviews_rating_number": "4.1", "reviews_amount": "(17)"},
{"name": "Aspiradora Yelmo As-3244 395ml Limpieza Del Hogar Celeste/naranja", "seller": "Por Yelmo ", "price": "125.004", "reviews_rating_number": "4.5", "reviews_amount": "(2)"},
{"name": "Aspiradora Ultracomb As4220 Filtro Hepa 1,2 Litros 1600w", "seller": "Por IOW Insumos Odontologicos Web ", "price": "113.000", "reviews_rating_number": null, "reviews_amount": null},
{"name": "Aspiradora Yelmo As3323 Agua Y Polvo 1400w 23 Lts Color Verde/Gris", "seller": "Por AJAXGOLD ", "price": "86.950", "reviews_rating_number": "4.7", "reviews_amount": "(4285)"},
{"name": "Aspiradora Ultracomb As-4220 Sin Bolsa 1600w Filtro Hepa Ep", "seller": "Por Isern Hogar ", "price": "79.545", "reviews_rating_number": null, "reviews_amount": null},
{"name": "Aspiradora De Tacho Gadnic Alta Potencia Gran Capacidad Color Gris oscuro", "seller": "Por Bidcom ", "price": "122.699", "reviews_rating_number": "4.6", "reviews_amount": "(38)"},
{"name": "Aspiradora Ultracomb As4224 1800w Sin Bolsa 2.5l Filtro Hepa", "seller": "Por IOW Insumos Odontologicos Web ", "price": "105.999", "reviews_rating_number": "4.7", "reviews_amount": "(92)"},
{"name": "Aspiradora Ultracomb As-4230 2200w 7 Litros Filtro Hepa Plata", "seller": "Por Tiendasur ", "price": "382.403", "reviews_rating_number": "4.7", "reviews_amount": "(3)"},
{"name": "Aspiradora Recargable Yelmo As-3244 Usb Luz Led Filtro He.pa", "seller": null, "price": "45.299", "reviews_rating_number": null, "reviews_amount": null},
{"name": "Aspiradora Ultracomb As4228 2000w Filtro Hepa", "seller": "Por IOW Insumos Odontologicos Web ", "price": "269.999", "reviews_rating_number": null, "reviews_amount": null},
{"name": "Aspiradora Ultracomb As-4220 Sin Bolsa 1600w Filtro Hepa Ep", "seller": "Por Distribuidora MAYA ", "price": "99.999", "reviews_rating_number": null, "reviews_amount": null},
{"name": "Aspiradora Yelmo As3323 Agua Y Polvo 1400w 23l Color Verde Verde/gris", "seller": "Por Yelmo ", "price": "213.784", "reviews_rating_number": "4.3", "reviews_amount": "(6)"},
{"name": "Aspiradora Ultracomb As4224 1800w Sin Bolsa 2.5l Filtro Hepa", "seller": "Por IOW Insumos Odontologicos Web ", "price": "145.799", "reviews_rating_number": "4.0", "reviews_amount": "(3)"},
{"name": "Aspiradora Recargable Yelmo As-3244 Usb Luz Led Filtro Hep Celeste/naranja", "seller": null, "price": "125.004", "reviews_rating_number": null, "reviews_amount": null},
{"name": "Aspiradora Ultracomb As-4230 2200w 7lts Filtro Hepa Lavable", "seller": null, "price": "249.999", "reviews_rating_number": null, "reviews_amount": null},
{"name": "Aspiradora Yelmo As3323 Agua Y Polvo 1400w 23l Color Verde Verde/gris", "seller": "Por Yelmo ", "price": "213.784", "reviews_rating_number": null, "reviews_amount": null},
{"name": "Aspiradora Ultracomb As-4220 Sin Bolsa 1600w Filtro Hepa Gris/naranja", "seller": null, "price": "99.000", "reviews_rating_number": null, "reviews_amount": null},
{"name": "Aspiradora Ultracomb As4220 Filtro Hepa 1,2 Litros 1600w Gris/naranja", "seller": null, "price": "99.940", "reviews_rating_number": "4.5", "reviews_amount": "(2)"},
{"name": "Aspiradora Ultracomb As4220 Filtro Hepa 1,2 Litros 1600w", "seller": "Por HIPERHOGAR ", "price": "99.940", "reviews_rating_number": "3.9", "reviews_amount": "(7)"},
{"name": "Aspiradora Ultracomb As-4220 Sin Bolsa 1600w Filtro Hepa Ep Gris/naranja", "seller": null, "price": "95.174", "reviews_rating_number": null, "reviews_amount": null},
{"name": "Aspiradora Ultracomb As-4220 Sin Bolsa 1600w Filtro Hepa", "seller": null, "price": "123.573", "reviews_rating_number": null, "reviews_amount": null},
{"name": "Aspiradora Ultracomb As-4220 Sin Bolsa 1600w Filtro Hepa Ep ", "seller": "Por Tecnocenter ", "price": "84.500", "reviews_rating_number": "4.3", "reviews_amount": "(3)"},
{"name": "Aspiradora Yelmo As3323 Agua Y Polvo 1400w - Aj Hogar ", "seller": null, "price": "126.400", "reviews_rating_number": "5.0", "reviews_amount": "(1)"},
{"name": "Aspiradora Ultracomb As-4220 Sin Bolsa 1600w Filtro Hepa Ep", "seller": null, "price": "145.000", "reviews_rating_number": null, "reviews_amount": null},
{"name": "Aspiradora Yelmo As-3244 395ml Limpieza Del Hogar Celeste/naranja", "seller": "Por Yelmo ", "price": "125.004", "reviews_rating_number": "4.5", "reviews_amount": "(2)"},
{"name": "Yelmo As-3240 Aspiradora Para Auto Recargable Usb Color Gris", "seller": null, "price": "59.899", "reviews_rating_number": "4.4", "reviews_amount": "(13143)"},
{"name": "Aspiradora ultracomb As-4201 1400w 2l trineo bolsa cepillo color rojo", "seller": "Por EMAQTOOLS ", "price": "94.007", "reviews_rating_number": "4.5", "reviews_amount": "(3792)"},
{"name": "Aspiradora Gadnic De Tacho Alto Rendimiento Doméstico 20 Litros 1200W", "seller": "Por Gadnic ", "price": "159.599", "reviews_rating_number": "4.6", "reviews_amount": "(42)"},
{"name": "Aspiradora Vertical De Mano Ah400 2 En 1 Multifunción 1200 Ml 400w Belarra Frecuencia 50 Hz", "seller": "Por Belarra ", "price": "135.494", "reviews_rating_number": "4.6", "reviews_amount": "(1355)"},
{"name": "Aspiradora Yelmo As3228 2000w 3,5lts Sin Bolsa Filtro Hepa Color Rosa", "seller": null, "price": "159.999", "reviews_rating_number": "4.8", "reviews_amount": "(1274)"},
{"name": "Yelmo As3210 Aspiradora Super Compacta 1100 C/bolsa Poderosa", "seller": null, "price": "119.999", "reviews_rating_number": "4.6", "reviews_amount": "(9)"},
{"name": "Aspiradora Ultracomb As4220 Filtro Hepa 1,2 Litros 1600w", "seller": "Por IOW Insumos Odontologicos Web ", "price": "83.000", "reviews_rating_number": "4.1", "reviews_amount": "(17)"},
{"name": "Aspiradora Recargable Yelmo As-3244 Usb Led Filtro H.e.p.a Turquesa", "seller": null, "price": "54.000", "reviews_rating_number": null, "reviews_amount": null},
{"name": "Aspiradora Vertical De Mano 500w - Filtro Hepa Y Accesorios Turquesa", "seller": "Por Herrabox ", "price": "99.990", "reviews_rating_number": null, "reviews_amount": null},
{"name": "Aspiradora Para Auto Y Hogar Yelmo As-3240 Recargable Usb C", "seller": null, "price": "40.799", "reviews_rating_number": "4.1", "reviews_amount": "(7)"},
{"name": "Aspiradora Ultracomb As-4201 1400w 2l Trineo Bolsa Cepillo C", "seller": null, "price": "79.999", "reviews_rating_number": null, "reviews_amount": null},
{"name": "Aspiradora Recargable Yelmo As-3244 Usb Luz Led Filtro He.pa", "seller": null, "price": "45.299", "reviews_rating_number": null, "reviews_amount": null},
{"name": "Aspiradora Recargable Yelmo As-3244 Usb Luz Led Filtro Hep Celeste/naranja", "seller": null, "price": "125.004", "reviews_rating_number": null, "reviews_amount": null},
{"name": "Aspiradora Yelmo As3224 1600w Filtro Hepa Rosa Rosa Chicle", "seller": "Por Tidi ", "price": "180.499", "reviews_rating_number": null, "reviews_amount": null},
{"name": "Aspiradora Ultracomb As-4201 Con Bolsa Alfombra 1400w 2 Lts", "seller": "Por Electro Point ", "price": "71.849", "reviews_rating_number": "4.4", "reviews_amount": "(17)"},
{"name": "Aspiradora De Mano Vertical 2 En 1 400w Belarra Ah400 Beige", "seller": "Por Belarra ", "price": "135.494", "reviews_rating_number": "4.7", "reviews_amount": "(63)"},
{"name": "Aspiradora Yelmo As3210 Compacta 1100 Con Bolsa Y Accesorio Verde", "seller": "Por Servibaires ", "price": "134.068", "reviews_rating_number": "4.3", "reviews_amount": "(10)"},
{"name": "Aspiradora Yelmo As3224 Sin Bolsa 1600w. 2 Lts Filtro Hepa  Rosa/gris", "seller": "Por SERVICE BAIRES ", "price": "183.038", "reviews_rating_number": null, "reviews_amount": null},
{"name": "Aspiradora Recargable Yelmo As-3244 Usb Luz Led Filtro Hepa", "seller": "Por IOW Insumos Odontologicos Web ", "price": "80.000", "reviews_rating_number": null, "reviews_amount": null},
{"name": "Aspiradora Ultracomb As4220 Filtro Hepa 1,2 Litros 1600w", "seller": "Por IOW Insumos Odontologicos Web ", "price": "113.000", "reviews_rating_number": null, "reviews_amount": null},
{"name": "Aspiradora Para Auto Yelmo As3240 Recargable Usb Filtro Hepa Gris", "seller": "Por TIO MUSA ", "price": "41.999", "reviews_rating_number": null, "reviews_amount": null},
{"name": "Aspiradora Yelmo As-3210 2.5l 1100 W Bolsa Recolectora", "seller": null, "price": "89.998", "reviews_rating_number": null, "reviews_amount": null},
{"name": "Aspiradora Yelmo As-3210 1100w Compacta Hogar Autos", "seller": null, "price": "179.414", "reviews_rating_number": null, "reviews_amount": null},
{"name": "Aspiradora Ultracomb As-4201 1400w 2l Trineo Bolsa Cepillo", "seller": "Por Morashop ", "price": "104.312", "reviews_rating_number": null, "reviews_amount": null},
{"name": "Aspiradora Recargable Yelmo As-3240 Hogar Y Auto Usb - Hepa", "seller": "Por Grupo Marquez ", "price": "50.299", "reviews_rating_number": null, "reviews_amount": null},
{"name": "Aspiradora Yelmo As-3240 Recargable De Mano 80w Usb", "seller": null, "price": "42.999", "reviews_rating_number": null, "reviews_amount": null},
{"name": "Aspiradora Ultracomb As-4220 Sin Bolsa 1600w Filtro Hepa Ep", "seller": null, "price": "145.000", "reviews_rating_number": null, "reviews_amount": null},
{"name": "Aspiradora Recargable Yelmo As-3244 Usb Led Filtro H.e.p.a Turquesa", "seller": null, "price": "54.000", "reviews_rating_number": null, "reviews_amount": null},
{"name": "Aspiradora Ultracomb As-4220 Sin Bolsa 1600w Filtro Hepa Gris/naranja", "seller": null, "price": "99.000", "reviews_rating_number": null, "reviews_amount": null},
{"name": "Aspiradora Yelmo As-3244 395ml Limpieza Del Hogar Celeste/naranja", "seller": "Por Yelmo ", "price": "125.004", "reviews_rating_number": "4.5", "reviews_amount": "(2)"},
{"name": "Aspiradora Recargable Yelmo As-3244 Usb Luz Led Filtro Hepa", "seller": "Por IOW Insumos Odontologicos Web ", "price": "80.000", "reviews_rating_number": null, "reviews_amount": null},
{"name": "Aspiradora Yelmo As3228 2000w 3,5lts Sin Bolsa Filtro Hepa Color Rosa", "seller": null, "price": "159.999", "reviews_rating_number": "4.8", "reviews_amount": "(1274)"},
{"name": "Aspiradora Recargable Yelmo As-3244 Usb Luz Led Filtro H.e.p.a Turquesa", "seller": null, "price": "99.999", "reviews_rating_number": "4.4", "reviews_amount": "(158)"},
{"name": "Aspiradora Ultracomb As-4220 Sin Bolsa 1600w Filtro Hepa Ep", "seller": "Por Isern Hogar ", "price": "79.545", "reviews_rating_number": null, "reviews_amount": null},
{"name": "Aspiradora Yelmo As-3228 Trineo 50hz", "seller": "Por IOW Insumos Odontologicos Web ", "price": "284.434", "reviews_rating_number": "4.8", "reviews_amount": "(1274)"},
{"name": "Aspiradora Ultracomb Sin Bolsa As4228 2000w Filtro Hepa Gris/naranja", "seller": null, "price": "137.786", "reviews_rating_number": null, "reviews_amount": null},
{"name": "Aspiradora Ultracomb As4308 Filtro Hepa 18l Aspira Liquido", "seller": null, "price": "87.008", "reviews_rating_number": null, "reviews_amount": null},
{"name": "Aspiradora Recargable Yelmo As-3240 Hogar Y Auto Usb - Hepa", "seller": "Por Grupo Marquez ", "price": "50.299", "reviews_rating_number": null, "reviews_amount": null},
{"name": "Aspiradora Ultracomb As-4220 Sin Bolsa 1600w Filtro Hepa Ep", "seller": "Por Distribuidora MAYA ", "price": "99.999", "reviews_rating_number": null, "reviews_amount": null},
{"name": "Aspiradora Ultracomb As4220 Filtro Hepa 1,2 Litros 1600w", "seller": "Por IOW Insumos Odontologicos Web ", "price": "83.000", "reviews_rating_number": "4.1", "reviews_amount": "(17)"},
{"name": "Aspiradora Recargable Yelmo As-3244 Usb Luz Led Filtro He.pa", "seller": null, "price": "45.299", "reviews_rating_number": null, "reviews_amount": null},
{"name": "Aspiradora Recargable Yelmo As-3244 Usb Luz Led Filtro Hep Celeste/naranja", "seller": null, "price": "125.004", "reviews_rating_number": null, "reviews_amount": null},
{"name": "Aspiradora Ultracomb As4228 2000w Filtro Hepa", "seller": "Por IOW Insumos Odontologicos Web ", "price": "269.999", "reviews_rating_number": null, "reviews_amount": null},
{"name": "Aspiradora Ultracomb As-4220 Sin Bolsa 1600w Filtro Hepa Ep Gris/naranja", "seller": null, "price": "95.174", "reviews_rating_number": null, "reviews_amount": null},
{"name": "Aspiradora Ultracomb As4220 Filtro Hepa 1,2 Litros 1600w", "seller": "Por IOW Insumos Odontologicos Web ", "price": "113.000", "reviews_rating_number": null, "reviews_amount": null},
{"name": "Aspiradora Ultracomb As-4220 Sin Bolsa 1600w Filtro Hepa", "seller": null, "price": "123.573", "reviews_rating_number": null, "reviews_amount": null},
{"name": "Aspiradora Sin Bolsa Yelmo As-3228 3.5l 2000w Filtro Hepa", "seller": null, "price": "223.999", "reviews_rating_number": "5.0", "reviews_amount": "(1)"},
{"name": "Aspiradora Ultracomb As-4220 Sin Bolsa 1600w Filtro Hepa Ep ", "seller": "Por Tecnocenter ", "price": "84.500", "reviews_rating_number": "4.3", "reviews_amount": "(3)"},
{"name": "Aspiradora Yelmo As-3228 2000w Filtro Hepa Gris Rosa", "seller": null, "price": "332.650", "reviews_rating_number": null, "reviews_amount": null},
{"name": "Aspiradora Yelmo As-3228 Filtro Hepa 3.5l Multi-ciclónica  Gris/rosa", "seller": null, "price": "230.399", "reviews_rating_number": null, "reviews_amount": null},
{"name": "Aspiradora Ultracomb As-4220 Sin Bolsa 1600w Filtro Hepa Ep", "seller": null, "price": "145.000", "reviews_rating_number": null, "reviews_amount": null},
{"name": "Aspiradora Recargable Yelmo As-3244 Usb Luz Led Filtro Hep Celeste/naranja", "seller": null, "price": "125.004", "reviews_rating_number": null, "reviews_amount": null},
{"name": "Aspiradora Yelmo As-3244 395ml Limpieza Del Hogar Celeste/naranja", "seller": "Por Yelmo ", "price": "125.004", "reviews_rating_number": "4.5", "reviews_amount": "(2)"},
{"name": "Aspiradora Recargable Yelmo As-3244 Usb Luz Led Filtro Hepa", "seller": "Por IOW Insumos Odontologicos Web ", "price": "80.000", "reviews_rating_number": null, "reviews_amount": null},
{"name": "Yelmo As-3240 Aspiradora Para Auto Recargable Usb Color Gris", "seller": null, "price": "59.899", "reviews_rating_number": "4.4", "reviews_amount": "(13143)"},
{"name": "Aspiradora Yelmo As3228 2000w 3,5lts Sin Bolsa Filtro Hepa Color Rosa", "seller": null, "price": "159.999", "reviews_rating_number": "4.8", "reviews_amount": "(1274)"},
{"name": "Aspiradora Yelmo As-3228 Trineo 50hz", "seller": "Por IOW Insumos Odontologicos Web ", "price": "284.434", "reviews_rating_number": "4.8", "reviews_amount": "(1274)"},
{"name": "Aspiradora Yelmo As 3224 2lts Filtro S/bolsa Hepa 1600w Color Gris/Azul", "seller": null, "price": "149.999", "reviews_rating_number": "4.7", "reviews_amount": "(779)"},
{"name": "Aspiradora Recargable Yelmo As-3244 Usb Luz Led Filtro H.e.p.a Turquesa", "seller": null, "price": "99.999", "reviews_rating_number": "4.4", "reviews_amount": "(158)"},
{"name": "Aspiradora Yelmo As3224 Sin Bolsa 1600w. 2 Lts Filtro Hepa  Rosa/gris", "seller": "Por SERVICE BAIRES ", "price": "183.038", "reviews_rating_number": null, "reviews_amount": null},
{"name": "Aspiradora C/bolsa Yelmo Canister As-3210 1100w ", "seller": null, "price": "142.550", "reviews_rating_number": null, "reviews_amount": null},
{"name": "Aspiradora Recargable Yelmo As-3244 Usb Luz Led Filtro Hepa", "seller": "Por IOW Insumos Odontologicos Web ", "price": "58.500", "reviews_rating_number": null, "reviews_amount": null},
{"name": "Aspiradora Recargable Yelmo As-3244 Usb Led Filtro H.e.p.a Turquesa", "seller": null, "price": "54.000", "reviews_rating_number": null, "reviews_amount": null},
{"name": "Aspiradora Recargable Yelmo As-3244 Usb Luz Led Filtro He.pa", "seller": null, "price": "45.299", "reviews_rating_number": null, "reviews_amount": null},
{"name": "Aspiradora Recargable Inalambrica Sin Bolsa De Mano As3244 E", "seller": "Por Electro Point ", "price": "44.549", "reviews_rating_number": "5.0", "reviews_amount": "(1)"},
{"name": "Aspiradora Yelmo 2000w 3.5 Lts As-3228 Sin Bolsa Filtro Hepa", "seller": "Por Electro Point ", "price": "116.299", "reviews_rating_number": "4.7", "reviews_amount": "(75)"},
{"name": "Aspiradora Yelmo Sin Bolsa As-3224 1600w  2lts Filtro Hepa", "seller": "Por Electro Point ", "price": "100.979", "reviews_rating_number": "4.6", "reviews_amount": "(46)"},
{"name": "Yelmo As-3240 Aspiradora Recargable Usb Gris 395 Ml Gris", "seller": "Por Yelmo ", "price": "88.894", "reviews_rating_number": null, "reviews_amount": null},
{"name": "Aspiradora Recargable Yelmo As-3240 Hogar Y Auto Usb - Hepa", "seller": "Por Grupo Marquez ", "price": "50.299", "reviews_rating_number": null, "reviews_amount": null},
{"name": "Aspiradora Sin Bolsa Yelmo As-3228 3.5l 2000w Filtro Hepa", "seller": null, "price": "223.999", "reviews_rating_number": "5.0", "reviews_amount": "(1)"},
{"name": "Aspiradora Yelmo As-3240 Recargable De Mano 80w Usb", "seller": null, "price": "42.999", "reviews_rating_number": null, "reviews_amount": null},
{"name": "Aspiradora Yelmo As-3228 2000w Filtro Hepa Gris Rosa", "seller": null, "price": "332.650", "reviews_rating_number": null, "reviews_amount": null},
{"name": "Aspiradora De Mano Yelmo As-3240", "seller": null, "price": "49.113", "reviews_rating_number": "5.0", "reviews_amount": "(1)"},
{"name": "Aspiradora Yelmo Para Automovil Azul As-3239", "seller": null, "price": "35.999", "reviews_rating_number": null, "reviews_amount": null},
{"name": "Aspiradora Yelmo As 3224 2lts Filtro S/bolsa Hepa 1600w Color Gris/Azul", "seller": "Por GRAMABI ", "price": "187.400", "reviews_rating_number": "4.7", "reviews_amount": "(779)"},
{"name": "Aspiradora Recargable Yelmo As-3244 Usb Luz Led Filtro Hep Celeste/naranja", "seller": null, "price": "125.004", "reviews_rating_number": null, "reviews_amount": null},
{"name": "Aspiradora Yelmo As-3244 395ml Limpieza Del Hogar Celeste/naranja", "seller": "Por Yelmo ", "price": "125.004", "reviews_rating_number": "4.5", "reviews_amount": "(2)"},
{"name": "Aspiradora Recargable Yelmo As-3244 Usb Luz Led Filtro H.e.p.a Turquesa", "seller": null, "price": "99.999", "reviews_rating_number": "4.4", "reviews_amount": "(158)"},
{"name": "Aspiradora Yelmo As 3224 2,5lts Filtro S/bolsa Hepa 1600w Color Rosa/gris", "seller": null, "price": "89.986", "reviews_rating_number": "4.7", "reviews_amount": "(502)"},
{"name": "Aspiradora Yelmo As 3224 2lts Filtro S/bolsa Hepa 1600w Color Gris/Azul", "seller": null, "price": "149.999", "reviews_rating_number": "4.7", "reviews_amount": "(779)"},
{"name": "Aspiradora Para Auto Y Hogar Yelmo As-3240 Recargable Usb C", "seller": null, "price": "40.799", "reviews_rating_number": "4.1", "reviews_amount": "(7)"},
{"name": "Aspiradora Ultracomb As4220 Filtro Hepa 1,2 Litros 1600w", "seller": "Por IOW Insumos Odontologicos Web ", "price": "83.000", "reviews_rating_number": "4.1", "reviews_amount": "(17)"},
{"name": "Aspiradora Recargable Yelmo As-3244 Usb Luz Led Filtro Hepa", "seller": "Por IOW Insumos Odontologicos Web ", "price": "58.500", "reviews_rating_number": null, "reviews_amount": null},
{"name": "Aspiradora Yelmo As 3224 2lts Filtro S/bolsa Hepa 1600w 220v Gris/azul", "seller": "Por GRAMABI ", "price": "187.400", "reviews_rating_number": null, "reviews_amount": null},
{"name": "Aspiradora Recargable Yelmo As-3244 Usb Led Filtro H.e.p.a Turquesa", "seller": null, "price": "54.000", "reviews_rating_number": null, "reviews_amount": null},
{"name": "Aspiradora Recargable Yelmo As-3244 Usb Luz Led Filtro He.pa", "seller": null, "price": "45.299", "reviews_rating_number": null, "reviews_amount": null},
{"name": "Aspiradora Yelmo As3224 1600w Filtro Hepa Rosa Rosa Chicle", "seller": "Por Tidi ", "price": "180.499", "reviews_rating_number": null, "reviews_amount": null},
{"name": "Aspiradora Yelmo As 3224 2,5lts Filtro S/bolsa Hepa 1600 Rosa/gris", "seller": "Por SERVICE BAIRES ", "price": "138.661", "reviews_rating_number": null, "reviews_amount": null},
{"name": "Aspiradora Yelmo As-3228 Trineo 50hz", "seller": "Por IOW Insumos Odontologicos Web ", "price": "284.434", "reviews_rating_number": "4.8", "reviews_amount": "(1274)"},
{"name": "Aspiradora Ultracomb As-4220 Sin Bolsa 1600w Filtro Hepa Gris/naranja", "seller": null, "price": "99.000", "reviews_rating_number": null, "reviews_amount": null},
{"name": "Aspiradora Recargable Yelmo As-3244 Usb Luz Led Filtro Hepa", "seller": "Por IOW Insumos Odontologicos Web ", "price": "80.000", "reviews_rating_number": null, "reviews_amount": null},
{"name": "Aspiradora Yelmo As 3224 2lts Filtro S/bolsa Hepa 1600w 220v", "seller": "Por Tecnocenter ", "price": "124.320", "reviews_rating_number": "4.9", "reviews_amount": "(8)"},
{"name": "Aspiradora Para Auto Yelmo As3240 Recargable Usb Filtro Hepa Gris", "seller": "Por TIO MUSA ", "price": "41.999", "reviews_rating_number": null, "reviews_amount": null},
{"name": "Aspiradora Yelmo As3210 Filtro Lavable 1100w 2,5lts Tio Musa Verde/gris", "seller": "Por TIO MUSA ", "price": "67.999", "reviews_rating_number": null, "reviews_amount": null},
{"name": "Aspiradora Yelmo As3224 Sin Bolsa 1600w. 2 Lts Filtro Hepa  Rosa/gris", "seller": "Por SERVICE BAIRES ", "price": "183.038", "reviews_rating_number": null, "reviews_amount": null},
{"name": "Aspiradora Recargable Yelmo As-3244 Usb Luz Led Filtro Lh", "seller": "Por LHCONFORT ", "price": "95.999", "reviews_rating_number": null, "reviews_amount": null},
{"name": "Aspiradora Ultracomb As4220 Filtro Hepa 1,2 Litros 1600w", "seller": "Por IOW Insumos Odontologicos Web ", "price": "113.000", "reviews_rating_number": null, "reviews_amount": null},
{"name": "Aspiradora Yelmo As 3224 2lts Filtro S/bolsa Hepa 1600w", "seller": null, "price": "158.008", "reviews_rating_number": null, "reviews_amount": null},
{"name": "Aspiradora Recargable Yelmo As-3240 Hogar Y Auto Usb - Hepa", "seller": "Por Grupo Marquez ", "price": "50.299", "reviews_rating_number": null, "reviews_amount": null},
{"name": "Aspiradora Sin Bolsa Yelmo As-3228 3.5l 2000w Filtro Hepa", "seller": null, "price": "223.999", "reviews_rating_number": "5.0", "reviews_amount": "(1)"},
{"name": "Aspiradora Ultracomb As-4220 Sin Bolsa 1600w Filtro Hepa Ep ", "seller": "Por Tecnocenter ", "price": "84.500", "reviews_rating_number": "4.3", "reviews_amount": "(3)"},
{"name": "Aspiradora Yelmo As-3224 1600w Filtro Hepa Azul", "seller": null, "price": "192.850", "reviews_rating_number": "4.0", "reviews_amount": "(1)"},
{"name": "Aspiradora De Mano Yelmo As-3240", "seller": null, "price": "49.113", "reviews_rating_number": "5.0", "reviews_amount": "(1)"},
{"name": "Aspiradora Yelmo As-3224 1600w Filtro Hepa Azul", "seller": null, "price": "174.999", "reviews_rating_number": null, "reviews_amount": null},
{"name": "Aspiradora Yelmo As-3224 1600w Filtro Hepa Azul", "seller": null, "price": "199.999", "reviews_rating_number": null, "reviews_amount": null},
{"name": "Aspiradora Ultracomb As-4220 Sin Bolsa 1600w Filtro Hepa Ep", "seller": null, "price": "145.000", "reviews_rating_number": null, "reviews_amount": null},
{"name": "Aspiradora Yelmo As3228 2000w 3,5lts Sin Bolsa Filtro Hepa Color Rosa", "seller": null, "price": "159.999", "reviews_rating_number": "4.8", "reviews_amount": "(1274)"},
{"name": "Aspiradora Yelmo As-3244 395ml Limpieza Del Hogar Celeste/naranja", "seller": "Por Yelmo ", "price": "125.004", "reviews_rating_number": "4.5", "reviews_amount": "(2)"},
{"name": "Aspiradora Yelmo 2000w 3.5 Lts As-3228 Sin Bolsa Filtro Hepa", "seller": "Por Electro Point ", "price": "116.299", "reviews_rating_number": "4.7", "reviews_amount": "(75)"},
{"name": "Aspiradora Gadnic 700w Limpia Tapizado Con Accesorios Color Blanco", "seller": "Por Bidcom ", "price": "230.499", "reviews_rating_number": "4.3", "reviews_amount": "(4)"},
{"name": "Aspiradora De Tacho Gadnic Alta Potencia Gran Capacidad Color Gris oscuro", "seller": "Por Bidcom ", "price": "122.699", "reviews_rating_number": "4.6", "reviews_amount": "(38)"},
{"name": "Aspiradora De Mano Vertical 2 En 1 600w Belarra Ah600", "seller": "Por Belarra ", "price": "169.009", "reviews_rating_number": "4.6", "reviews_amount": "(306)"},
{"name": "Aspiradora Ultracomb As4220 Filtro Hepa 1,2 Litros 1600w", "seller": "Por IOW Insumos Odontologicos Web ", "price": "83.000", "reviews_rating_number": "4.1", "reviews_amount": "(17)"},
{"name": "Aspiradora Yelmo As3224 1600w Filtro Hepa Rosa Rosa Chicle", "seller": "Por Tidi ", "price": "180.499", "reviews_rating_number": null, "reviews_amount": null},
{"name": "Aspiradora Ultracomb As-4220 Sin Bolsa 1600w Filtro Hepa Gris/naranja", "seller": null, "price": "99.000", "reviews_rating_number": null, "reviews_amount": null},
{"name": "Aspiradora Yelmo As3224 Sin Bolsa 1600w. 2 Lts Filtro Hepa  Rosa/gris", "seller": "Por SERVICE BAIRES ", "price": "183.038", "reviews_rating_number": null, "reviews_amount": null},
{"name": "Aspiradora Sin Bolsa Yelmo As-3228 3.5l 2000w Filtro Hepa", "seller": null, "price": "223.999", "reviews_rating_number": "5.0", "reviews_amount": "(1)"},
{"name": "Aspiradora Yelmo As-3224 1600w Filtro Hepa Azul", "seller": null, "price": "200.750", "reviews_rating_number": null, "reviews_amount": null},
{"name": "Aspiradora Ultracomb As4220 Filtro Hepa 1,2 Litros 1600w", "seller": "Por IOW Insumos Odontologicos Web ", "price": "113.000", "reviews_rating_number": null, "reviews_amount": null},
{"name": "Aspiradora Yelmo As-3228 2000w Filtro Hepa Gris Rosa Gris/rosa", "seller": null, "price": "263.575", "reviews_rating_number": null, "reviews_amount": null},
{"name": "Aspiradora Yelmo As-3224 1600w Filtro Hepa Azul", "seller": null, "price": "192.850", "reviews_rating_number": "4.0", "reviews_amount": "(1)"},
{"name": "Aspiradora Yelmo As-3228 2000w Filtro Hepa Gris Rosa", "seller": null, "price": "332.650", "reviews_rating_number": null, "reviews_amount": null},
{"name": "Aspiradora Yelmo As-3228 2000w Filtro Hepa Gris Rosa", "seller": null, "price": "302.399", "reviews_rating_number": null, "reviews_amount": null},
{"name": "Aspiradora Yelmo As-3228 2000w Filtro Hepa Gris Rosa", "seller": null, "price": "351.750", "reviews_rating_number": null, "reviews_amount": null},
{"name": "Aspiradora Yelmo As-3228 2000w Filtro Hepa Gris Rosa", "seller": null, "price": "282.875", "reviews_rating_number": null, "reviews_amount": null},
{"name": "Aspiradora Yelmo As-3228 2000w Filtro Hepa Gris Rosa", "seller": null, "price": "313.599", "reviews_rating_number": null, "reviews_amount": null},
{"name": "Aspiradora Yelmo As-3228 2000w Filtro Hepa Gris Rosa", "seller": null, "price": "255.999", "reviews_rating_number": null, "reviews_amount": null},
{"name": "Aspiradora Yelmo As-3228 2000w Filtro Hepa Gris Rosa", "seller": null, "price": "332.650", "reviews_rating_number": null, "reviews_amount": null},
{"name": "Aspiradora Yelmo As-3224 1600w Filtro Hepa Azul", "seller": null, "price": "174.999", "reviews_rating_number": null, "reviews_amount": null},
{"name": "Aspiradora Yelmo As-3224 1600w Filtro Hepa Azul", "seller": null, "price": "199.999", "reviews_rating_number": null, "reviews_amount": null},
{"name": "Aspiradora Yelmo As-3228 2000w Filtro Hepa Gris Rosa", "seller": null, "price": "302.399", "reviews_rating_number": null, "reviews_amount": null},
{"name": "Aspiradora Ultracomb As-4220 Sin Bolsa 1600w Filtro Hepa Ep", "seller": null, "price": "145.000", "reviews_rating_number": null, "reviews_amount": null},
{"name": "Aspiradora Yelmo As-3228 2000w Filtro Hepa Gris Rosa", "seller": null, "price": "347.750", "reviews_rating_number": null, "reviews_amount": null},
{"name": "Aspiradora Yelmo As-3228 2000w Filtro Hepa Gris Rosa", "seller": null, "price": "297.975", "reviews_rating_number": null, "reviews_amount": null},
{"name": "Aspiradora Recargable Yelmo As-3244 Usb Led Filtro H.e.p.a Turquesa", "seller": null, "price": "54.000", "reviews_rating_number": null, "reviews_amount": null},
{"name": "Yelmo As-3240 Aspiradora Recargable Usb Gris 395 Ml Gris", "seller": "Por Yelmo ", "price": "88.894", "reviews_rating_number": null, "reviews_amount": null},
{"name": "Aspiradora Recargable Yelmo As-3244 Usb Luz Led Filtro He.pa", "seller": null, "price": "45.299", "reviews_rating_number": null, "reviews_amount": null},
{"name": "Aspiradora Recargable Yelmo As-3244 Usb Luz Led Filtro Hep Celeste/naranja", "seller": null, "price": "125.004", "reviews_rating_number": null, "reviews_amount": null},
{"name": "Aspiradora Yelmo As3323 Agua Y Polvo 1400w 23 Lts Color Verde/Gris", "seller": "Por AJAXGOLD ", "price": "86.950", "reviews_rating_number": "4.7", "reviews_amount": "(4285)"},
{"name": "Yelmo As-3240 Aspiradora Para Auto Recargable Usb Color Gris", "seller": null, "price": "59.899", "reviews_rating_number": "4.4", "reviews_amount": "(13143)"},
{"name": "Aspiradora Recargable Yelmo As-3244 Usb Luz Led Filtro H.e.p.a Turquesa", "seller": null, "price": "99.999", "reviews_rating_number": "4.4", "reviews_amount": "(158)"},
{"name": "Aspiradora Ultracomb As4220 Filtro Hepa 1,2 Litros 1600w", "seller": "Por IOW Insumos Odontologicos Web ", "price": "83.000", "reviews_rating_number": "4.1", "reviews_amount": "(17)"},
{"name": "Aspiradora De Tacho Gadnic Alta Potencia Gran Capacidad Color Gris oscuro", "seller": "Por Bidcom ", "price": "122.699", "reviews_rating_number": "4.6", "reviews_amount": "(38)"},
{"name": "ASPIRADORA TRINEO AC720 2000W Smart-Tek", "seller": null, "price": "149.534", "reviews_rating_number": "4.7", "reviews_amount": "(126)"},
{"name": "Aspiradora Yelmo As3323 Agua Y Polvo 1400w 23l Color Verde Verde/gris", "seller": "Por Yelmo ", "price": "213.784", "reviews_rating_number": "4.3", "reviews_amount": "(6)"},
{"name": "Aspiradora Recargable Yelmo As-3244 Usb Luz Led Filtro Hepa", "seller": "Por IOW Insumos Odontologicos Web ", "price": "58.500", "reviews_rating_number": null, "reviews_amount": null},
{"name": "Aspiradora Yelmo As3323 Agua Y Polvo 1400w 23l Color Verde Verde/gris", "seller": "Por Yelmo ", "price": "213.784", "reviews_rating_number": null, "reviews_amount": null},
{"name": "Aspiradora Yelmo As3224 1600w Filtro Hepa Rosa Rosa Chicle", "seller": "Por Tidi ", "price": "180.499", "reviews_rating_number": null, "reviews_amount": null},
{"name": "Aspiradora Yelmo As-3244 395ml Limpieza Del Hogar Celeste/naranja", "seller": "Por Yelmo ", "price": "125.004", "reviews_rating_number": "4.5", "reviews_amount": "(2)"},
{"name": "Yelmo As-3240 Aspiradora Para Auto Recargable Usb Color Gris", "seller": "Por GAUSSONLINE ", "price": "57.838", "reviews_rating_number": null, "reviews_amount": null},
{"name": "Aspiradora Ultracomb As4220 Filtro Hepa 1,2 Litros 1600w", "seller": "Por IOW Insumos Odontologicos Web ", "price": "113.000", "reviews_rating_number": null, "reviews_amount": null},
{"name": "Aspiradora Yelmo As-3224 1600w Filtro Hepa Azul", "seller": null, "price": "174.999", "reviews_rating_number": null, "reviews_amount": null},
{"name": "Aspiradora Recargable Yelmo As-3244 Usb Luz Led Filtro Hepa", "seller": "Por IOW Insumos Odontologicos Web ", "price": "80.000", "reviews_rating_number": null, "reviews_amount": null},
{"name": "Aspiradora Para Auto Yelmo As3240 Recargable Usb Filtro Hepa Gris", "seller": "Por TIO MUSA ", "price": "41.999", "reviews_rating_number": null, "reviews_amount": null},
{"name": "Yelmo As-3240 Aspiradora Recargable Usb Gris 80w", "seller": null, "price": "59.899", "reviews_rating_number": null, "reviews_amount": null},
{"name": "Aspiradora Recargable Yelmo As-3240 Hogar Y Auto Usb - Hepa", "seller": "Por Grupo Marquez ", "price": "50.299", "reviews_rating_number": null, "reviews_amount": null},
{"name": "Aspiradora Yelmo As-3240 Recargable De Mano 80w Usb", "seller": null, "price": "42.999", "reviews_rating_number": null, "reviews_amount": null},
{"name": "Aspiradora Yelmo As-3224 1600w Filtro Hepa Azul", "seller": null, "price": "199.999", "reviews_rating_number": null, "reviews_amount": null},
{"name": "Aspiradora Para Auto Y Hogar Yelmo As-3240 Recargable Usb C", "seller": null, "price": "40.799", "reviews_rating_number": "4.1", "reviews_amount": "(7)"},
{"name": "Aspiradora De Tacho Gadnic Alta Potencia Gran Capacidad Color Gris oscuro", "seller": "Por Bidcom ", "price": "122.699", "reviews_rating_number": "4.6", "reviews_amount": "(38)"},
{"name": "Aspiradora Yelmo As-3244 395ml Limpieza Del Hogar Celeste/naranja", "seller": "Por Yelmo ", "price": "125.004", "reviews_rating_number": "4.5", "reviews_amount": "(2)"},
{"name": "Aspiradora Yelmo As3228 2000w 3,5lts Sin Bolsa Filtro Hepa Color Rosa", "seller": null, "price": "159.999", "reviews_rating_number": "4.8", "reviews_amount": "(1274)"},
{"name": "Yelmo As-3240 Aspiradora Para Auto Recargable Usb Color Gris", "seller": null, "price": "59.899", "reviews_rating_number": "4.4", "reviews_amount": "(13143)"},
{"name": "Yelmo As 3244 Aspiradora Inalambrica Recargable Usb", "seller": null, "price": "99.999", "reviews_rating_number": "4.3", "reviews_amount": "(4)"},
{"name": "Aspiradora de Tacho Gadnic 15L Silenciosa Sopladora 1200W", "seller": "Por Gadnic ", "price": "91.499", "reviews_rating_number": "4.6", "reviews_amount": "(98)"},
{"name": "Aspiradora Yelmo As3224 Sin Bolsa 1600w. 2 Lts Filtro Hepa  Rosa/gris", "seller": "Por SERVICE BAIRES ", "price": "183.038", "reviews_rating_number": null, "reviews_amount": null},
{"name": "Aspiradora Yelmo 2000w 3.5 Lts As-3228 Sin Bolsa Filtro Hepa", "seller": "Por Electro Point ", "price": "116.299", "reviews_rating_number": "4.7", "reviews_amount": "(75)"},
{"name": "Aspiradora Recargable Yelmo As-3244 Usb Luz Led Filtro Hepa", "seller": "Por IOW Insumos Odontologicos Web ", "price": "58.500", "reviews_rating_number": null, "reviews_amount": null},
{"name": "Aspiradora Recargable Yelmo As-3244 Usb Led Filtro H.e.p.a Turquesa", "seller": null, "price": "54.000", "reviews_rating_number": null, "reviews_amount": null},
{"name": "Aspiradora Recargable Yelmo As-3244 Usb Luz Led Filtro He.pa", "seller": null, "price": "45.299", "reviews_rating_number": null, "reviews_amount": null},
{"name": "Aspiradora Recargable Yelmo As-3244 Usb Luz Led Filtro Hep Celeste/naranja", "seller": null, "price": "125.004", "reviews_rating_number": null, "reviews_amount": null},
{"name": "Yelmo As-3240 Aspiradora Recargable Usb Gris 395 Ml Gris", "seller": "Por Yelmo ", "price": "88.894", "reviews_rating_number": null, "reviews_amount": null},
{"name": "Aspiradora Recargable Yelmo As-3244 Usb Luz Led Filtro Hepa", "seller": "Por IOW Insumos Odontologicos Web ", "price": "80.000", "reviews_rating_number": null, "reviews_amount": null},
{"name": "Aspiradora Recargable Yelmo As-3240 Hogar Y Auto Usb - Hepa", "seller": "Por Grupo Marquez ", "price": "50.299", "reviews_rating_number": null, "reviews_amount": null},
{"name": "Aspiradora Sin Bolsa Yelmo As-3228 3.5l 2000w Filtro Hepa", "seller": null, "price": "223.999", "reviews_rating_number": "5.0", "reviews_amount": "(1)"},
{"name": "Aspiradora Yelmo As-3240 Recargable De Mano 80w Usb", "seller": null, "price": "42.999", "reviews_rating_number": null, "reviews_amount": null},
{"name": "Aspiradora Yelmo As-3228 2000w Filtro Hepa Gris Rosa", "seller": null, "price": "332.650", "reviews_rating_number": null, "reviews_amount": null},
{"name": "Aspiradora Yelmo As-3228 2000w Filtro Hepa Gris Rosa", "seller": null, "price": "351.750", "reviews_rating_number": null, "reviews_amount": null},
{"name": "Aspiradora Yelmo As-3228 2000w Filtro Hepa Gris Rosa", "seller": null, "price": "282.875", "reviews_rating_number": null, "reviews_amount": null},
{"name": "Aspiradora Yelmo As-3228 2000w Filtro Hepa Gris Rosa", "seller": null, "price": "313.599", "reviews_rating_number": null, "reviews_amount": null},
{"name": "Aspiradora Yelmo As-3228 2000w Filtro Hepa Gris Rosa", "seller": null, "price": "255.999", "reviews_rating_number": null, "reviews_amount": null},
{"name": "Aspiradora Yelmo As-3228 2000w Filtro Hepa Gris Rosa", "seller": null, "price": "332.650", "reviews_rating_number": null, "reviews_amount": null},
{"name": "Aspiradora Yelmo As-3228 2000w Filtro Hepa Gris Rosa", "seller": null, "price": "302.399", "reviews_rating_number": null, "reviews_amount": null},
{"name": "Aspiradora Yelmo As-3228 2000w Filtro Hepa Gris Rosa", "seller": null, "price": "347.750", "reviews_rating_number": null, "reviews_amount": null},
{"name": "Aspiradora Yelmo As-3228 2000w Filtro Hepa Gris Rosa", "seller": null, "price": "297.975", "reviews_rating_number": null, "reviews_amount": null},
{"name": "Aspiradora Yelmo As 3224 2lts Filtro S/bolsa Hepa 1600w Color Gris/Azul", "seller": "Por GRAMABI ", "price": "187.400", "reviews_rating_number": "4.7", "reviews_amount": "(779)"},
{"name": "Aspiradora Recargable Yelmo As-3244 Usb Luz Led Filtro Hep Celeste/naranja", "seller": null, "price": "125.004", "reviews_rating_number": null, "reviews_amount": null},
{"name": "Aspiradora Yelmo As3224 Sin Bolsa 1600w. 2 Lts Filtro Hepa  Rosa/gris", "seller": "Por SERVICE BAIRES ", "price": "183.038", "reviews_rating_number": null, "reviews_amount": null},
{"name": "Aspiradora Yelmo As-3244 395ml Limpieza Del Hogar Celeste/naranja", "seller": "Por Yelmo ", "price": "125.004", "reviews_rating_number": "4.5", "reviews_amount": "(2)"},
{"name": "Aspiradora Recargable Yelmo As-3244 Usb Luz Led Filtro Hepa", "seller": "Por IOW Insumos Odontologicos Web ", "price": "80.000", "reviews_rating_number": null, "reviews_amount": null},
{"name": "Aspiradora Recargable Yelmo As-3244 Usb Luz Led Filtro H.e.p.a Turquesa", "seller": null, "price": "99.999", "reviews_rating_number": "4.4", "reviews_amount": "(158)"},
{"name": "Aspiradora Yelmo As3228 2000w 3,5lts Sin Bolsa Filtro Hepa Color Rosa", "seller": null, "price": "159.999", "reviews_rating_number": "4.8", "reviews_amount": "(1274)"},
{"name": "Aspiradora Yelmo As 3224 2lts Filtro S/bolsa Hepa 1600w Color Gris/Azul", "seller": null, "price": "149.999", "reviews_rating_number": "4.7", "reviews_amount": "(779)"},
{"name": "Aspiradora Yelmo As-3210 2.5l  Verde Y Gris 220v Verde/gris", "seller": "Por Yelmo ", "price": "178.824", "reviews_rating_number": "4.5", "reviews_amount": "(2)"},
{"name": "Aspiradora Recargable Yelmo As-3244 Usb Luz Led Filtro Hepa", "seller": "Por IOW Insumos Odontologicos Web ", "price": "58.500", "reviews_rating_number": null, "reviews_amount": null},
{"name": "Aspiradora Recargable Yelmo As-3244 Usb Luz Led Filtro He.pa", "seller": null, "price": "45.299", "reviews_rating_number": null, "reviews_amount": null},
{"name": "Aspiradora Yelmo As3224 1600w Filtro Hepa Rosa Rosa Chicle", "seller": "Por Tidi ", "price": "180.499", "reviews_rating_number": null, "reviews_amount": null},
{"name": "Aspiradora Yelmo As-3210 2.5l 1100 W Bolsa Recolectora", "seller": null, "price": "89.998", "reviews_rating_number": null, "reviews_amount": null},
{"name": "Aspiradora Yelmo As3224 1600w 2l Sin Bolsa Filtro Hepa  Gris/azul", "seller": "Por Servibaires ", "price": "183.038", "reviews_rating_number": null, "reviews_amount": null},
{"name": "Yelmo As-3240 Aspiradora Recargable Usb Gris 395 Ml Gris", "seller": "Por Yelmo ", "price": "88.894", "reviews_rating_number": null, "reviews_amount": null},
{"name": "Aspiradora Sin Bolsa Yelmo As-3228 3.5l 2000w Filtro Hepa", "seller": null, "price": "223.999", "reviews_rating_number": "5.0", "reviews_amount": "(1)"},
{"name": "Aspiradora C/bolsa Yelmo Canister As-3210 1100w ", "seller": null, "price": "142.550", "reviews_rating_number": null, "reviews_amount": null},
{"name": "Yelmo Aspiradora As-3210 Canister 1100w 2,5l C/bolsa", "seller": null, "price": "148.999", "reviews_rating_number": null, "reviews_amount": null},
{"name": "Aspiradora Recargable Yelmo As-3240 Hogar Y Auto Usb - Hepa", "seller": "Por Grupo Marquez ", "price": "50.299", "reviews_rating_number": null, "reviews_amount": null},
{"name": "Aspiradora Yelmo As-3224 1600w Filtro Hepa Azul", "seller": null, "price": "200.750", "reviews_rating_number": null, "reviews_amount": null},
{"name": "Aspiradora Yelmo As-3224 1600w Filtro Hepa Azul", "seller": null, "price": "192.850", "reviews_rating_number": "4.0", "reviews_amount": "(1)"},
{"name": "Aspiradora Yelmo As-3228 2000w Filtro Hepa Gris Rosa", "seller": null, "price": "332.650", "reviews_rating_number": null, "reviews_amount": null},
{"name": "Aspiradora Yelmo As-3228 2000w Filtro Hepa Gris Rosa", "seller": null, "price": "351.750", "reviews_rating_number": null, "reviews_amount": null},
{"name": "Aspiradora Yelmo As-3228 2000w Filtro Hepa Gris Rosa", "seller": null, "price": "282.875", "reviews_rating_number": null, "reviews_amount": null},
{"name": "Aspiradora Yelmo As-3228 2000w Filtro Hepa Gris Rosa", "seller": null, "price": "313.599", "reviews_rating_number": null, "reviews_amount": null},
{"name": "Aspiradora Yelmo As-3228 2000w Filtro Hepa Gris Rosa", "seller": null, "price": "255.999", "reviews_rating_number": null, "reviews_amount": null},
{"name": "Aspiradora Yelmo As-3224 1600w Filtro Hepa Azul", "seller": null, "price": "231.425", "reviews_rating_number": null, "reviews_amount": null},
{"name": "Aspiradora Yelmo As-3228 2000w Filtro Hepa Gris Rosa", "seller": null, "price": "332.650", "reviews_rating_number": null, "reviews_amount": null},
{"name": "Aspiradora Yelmo As-3228 2000w Filtro Hepa Gris Rosa", "seller": null, "price": "302.399", "reviews_rating_number": null, "reviews_amount": null},
{"name": "Aspiradora Yelmo As-3228 2000w Filtro Hepa Gris Rosa", "seller": null, "price": "347.750", "reviews_rating_number": null, "reviews_amount": null},
{"name": "Aspiradora Yelmo As-3228 2000w Filtro Hepa Gris Rosa", "seller": null, "price": "297.975", "reviews_rating_number": null, "reviews_amount": null},
{"name": "Aspiradora Yelmo As 3224 2lts Filtro S/bolsa Hepa 1600w Color Gris/Azul", "seller": "Por GRAMABI ", "price": "187.400", "reviews_rating_number": "4.7", "reviews_amount": "(779)"},
{"name": "Aspiradora Yelmo As-3244 395ml Limpieza Del Hogar Celeste/naranja", "seller": "Por Yelmo ", "price": "125.004", "reviews_rating_number": "4.5", "reviews_amount": "(2)"},
{"name": "Aspiradora Yelmo As3224 Sin Bolsa 1600w. 2 Lts Filtro Hepa  Rosa/gris", "seller": "Por SERVICE BAIRES ", "price": "183.038", "reviews_rating_number": null, "reviews_amount": null},
{"name": "Aspiradora Recargable Yelmo As-3244 Usb Luz Led Filtro Hepa", "seller": "Por IOW Insumos Odontologicos Web ", "price": "80.000", "reviews_rating_number": null, "reviews_amount": null},
{"name": "Aspiradora Yelmo As3228 2000w 3,5lts Sin Bolsa Filtro Hepa Color Rosa", "seller": null, "price": "159.999", "reviews_rating_number": "4.8", "reviews_amount": "(1274)"},
{"name": "Aspiradora Recargable Yelmo As-3244 Usb Luz Led Filtro H.e.p.a Turquesa", "seller": null, "price": "99.999", "reviews_rating_number": "4.4", "reviews_amount": "(158)"},
{"name": "Aspiradora Yelmo As 3224 2lts Filtro S/bolsa Hepa 1600w Color Gris/Azul", "seller": null, "price": "149.999", "reviews_rating_number": "4.7", "reviews_amount": "(779)"},
{"name": "Aspiradora Para Auto Y Hogar Yelmo As-3240 Recargable Usb C", "seller": null, "price": "40.799", "reviews_rating_number": "4.1", "reviews_amount": "(7)"},
{"name": "Aspiradora Yelmo As-3210 2.5l  Verde Y Gris 220v Verde/gris", "seller": "Por Yelmo ", "price": "178.824", "reviews_rating_number": "4.5", "reviews_amount": "(2)"},
{"name": "Aspiradora Recargable Yelmo As-3244 Usb Luz Led Filtro Hepa", "seller": "Por IOW Insumos Odontologicos Web ", "price": "58.500", "reviews_rating_number": null, "reviews_amount": null},
{"name": "Aspiradora Recargable Yelmo As-3244 Usb Led Filtro H.e.p.a Turquesa", "seller": null, "price": "54.000", "reviews_rating_number": null, "reviews_amount": null},
{"name": "Aspiradora Recargable Yelmo As-3244 Usb Luz Led Filtro He.pa", "seller": null, "price": "45.299", "reviews_rating_number": null, "reviews_amount": null},
{"name": "Aspiradora Recargable Yelmo As-3244 Usb Luz Led Filtro Hep Celeste/naranja", "seller": null, "price": "125.004", "reviews_rating_number": null, "reviews_amount": null},
{"name": "Aspiradora Yelmo As3224 1600w Filtro Hepa Rosa Rosa Chicle", "seller": "Por Tidi ", "price": "180.499", "reviews_rating_number": null, "reviews_amount": null},
{"name": "Aspiradora Yelmo As-3210 2.5l 1100 W Bolsa Recolectora", "seller": null, "price": "89.998", "reviews_rating_number": null, "reviews_amount": null},
{"name": "Aspiradora Yelmo As3224 1600w 2l Sin Bolsa Filtro Hepa  Gris/azul", "seller": "Por Servibaires ", "price": "183.038", "reviews_rating_number": null, "reviews_amount": null},
{"name": "Aspiradora Recargable Yelmo As-3240 Hogar Y Auto Usb - Hepa", "seller": "Por Grupo Marquez ", "price": "50.299", "reviews_rating_number": null, "reviews_amount": null},
{"name": "Aspiradora Sin Bolsa Yelmo As-3228 3.5l 2000w Filtro Hepa", "seller": null, "price": "223.999", "reviews_rating_number": "5.0", "reviews_amount": "(1)"},
{"name": "Aspiradora C/bolsa Yelmo Canister As-3210 1100w ", "seller": null, "price": "142.550", "reviews_rating_number": null, "reviews_amount": null},
{"name": "Aspiradora Yelmo As-3210 1100w Compacta Hogar Autos", "seller": null, "price": "179.414", "reviews_rating_number": null, "reviews_amount": null},
{"name": "Aspiradora Yelmo As-3224 1600w Filtro Hepa Azul", "seller": null, "price": "200.750", "reviews_rating_number": null, "reviews_amount": null},
{"name": "Aspiradora Yelmo As-3224 1600w Filtro Hepa Azul", "seller": null, "price": "192.850", "reviews_rating_number": "4.0", "reviews_amount": "(1)"},
{"name": "Aspiradora Yelmo As-3228 2000w Filtro Hepa Gris Rosa", "seller": null, "price": "332.650", "reviews_rating_number": null, "reviews_amount": null},
{"name": "Aspiradora Yelmo As-3228 2000w Filtro Hepa Gris Rosa", "seller": null, "price": "302.399", "reviews_rating_number": null, "reviews_amount": null},
{"name": "Aspiradora Yelmo As-3228 2000w Filtro Hepa Gris Rosa", "seller": null, "price": "351.750", "reviews_rating_number": null, "reviews_amount": null},
{"name": "Aspiradora Yelmo As-3228 2000w Filtro Hepa Gris Rosa", "seller": null, "price": "282.875", "reviews_rating_number": null, "reviews_amount": null},
{"name": "Aspiradora Yelmo As-3228 2000w Filtro Hepa Gris Rosa", "seller": null, "price": "313.599", "reviews_rating_number": null, "reviews_amount": null},
{"name": "Aspiradora Yelmo As-3228 2000w Filtro Hepa Gris Rosa", "seller": null, "price": "255.999", "reviews_rating_number": null, "reviews_amount": null},
{"name": "Aspiradora Yelmo As-3224 1600w Filtro Hepa Azul", "seller": null, "price": "231.425", "reviews_rating_number": null, "reviews_amount": null},
{"name": "Aspiradora Yelmo As-3228 2000w Filtro Hepa Gris Rosa", "seller": null, "price": "332.650", "reviews_rating_number": null, "reviews_amount": null},
{"name": "Aspiradora Yelmo As-3228 2000w Filtro Hepa Gris Rosa", "seller": null, "price": "302.399", "reviews_rating_number": null, "reviews_amount": null},
{"name": "Aspiradora Yelmo As-3228 2000w Filtro Hepa Gris Rosa", "seller": null, "price": "347.750", "reviews_rating_number": null, "reviews_amount": null},
{"name": "Aspiradora Yelmo As-3228 2000w Filtro Hepa Gris Rosa", "seller": null, "price": "297.975", "reviews_rating_number": null, "reviews_amount": null},
{"name": "Aspiradora Yelmo As-3224 1600w Filtro Hepa Azul", "seller": null, "price": "208.675", "reviews_rating_number": null, "reviews_amount": null},
{"name": "Aspiradora Gadnic De Tacho Alto Rendimiento Doméstico 20 Litros 1200W", "seller": "Por Gadnic ", "price": "159.599", "reviews_rating_number": "4.6", "reviews_amount": "(42)"},
{"name": "Aspiradora De Tacho Gadnic Alta Potencia Gran Capacidad Color Gris oscuro", "seller": "Por Bidcom ", "price": "122.699", "reviews_rating_number": "4.6", "reviews_amount": "(38)"},
{"name": "Aspiradora Ultracomb As-4220 Sin Bolsa 1600w Filtro Hepa Ep", "seller": "Por Distribuidora MAYA ", "price": "99.999", "reviews_rating_number": null, "reviews_amount": null},
{"name": "Aspiradora de Tacho Gadnic 15L Silenciosa Sopladora 1200W", "seller": "Por Gadnic ", "price": "91.499", "reviews_rating_number": "4.6", "reviews_amount": "(98)"},
{"name": "Aspiradora Recargable Yelmo As-3244 Usb Led Filtro H.e.p.a Turquesa", "seller": null, "price": "54.000", "reviews_rating_number": null, "reviews_amount": null},
{"name": "Aspiradora Yelmo As3224 Sin Bolsa 1600w. 2 Lts Filtro Hepa  Rosa/gris", "seller": "Por SERVICE BAIRES ", "price": "183.038", "reviews_rating_number": null, "reviews_amount": null},
{"name": "Yelmo As-3240 Aspiradora Recargable Usb Gris 395 Ml Gris", "seller": "Por Yelmo ", "price": "88.894", "reviews_rating_number": null, "reviews_amount": null},
{"name": "Aspiradora C/bolsa Yelmo Canister As-3210 1100w ", "seller": null, "price": "142.550", "reviews_rating_number": null, "reviews_amount": null},
{"name": "Aspirador De Mano Portátil Gadnic ASP925 Hogar Automóvil Potente Succión", "seller": "Por Bidcom ", "price": "53.099", "reviews_rating_number": "4.3", "reviews_amount": "(132)"},
{"name": "Aspiradora Sin Bolsa Yelmo As-3228 3.5l 2000w Filtro Hepa", "seller": null, "price": "223.999", "reviews_rating_number": "5.0", "reviews_amount": "(1)"},
{"name": "Aspiradora Ultracomb As4220 Filtro Hepa 1,2 Litros 1600w", "seller": "Por IOW Insumos Odontologicos Web ", "price": "83.000", "reviews_rating_number": "4.1", "reviews_amount": "(17)"},
{"name": "Aspiradora Recargable Yelmo As-3244 Usb Luz Led Filtro He.pa", "seller": null, "price": "45.299", "reviews_rating_number": null, "reviews_amount": null},
{"name": "Aspiradora Recargable Yelmo As-3244 Usb Luz Led Filtro Hep Celeste/naranja", "seller": null, "price": "125.004", "reviews_rating_number": null, "reviews_amount": null},
{"name": "Aspiradora Yelmo As-3244 395ml Limpieza Del Hogar Celeste/naranja", "seller": "Por Yelmo ", "price": "125.004", "reviews_rating_number": "4.5", "reviews_amount": "(2)"},
{"name": "Aspiradora Ultracomb As-4220 Sin Bolsa 1600w Filtro Hepa Gris/naranja", "seller": null, "price": "99.000", "reviews_rating_number": null, "reviews_amount": null},
{"name": "Aspiradora Recargable Yelmo As-3244 Usb Luz Led Filtro Hepa", "seller": "Por IOW Insumos Odontologicos Web ", "price": "80.000", "reviews_rating_number": null, "reviews_amount": null},
{"name": "Aspiradora Ultracomb As-4220 Sin Bolsa 1600w Filtro Hepa Ep Gris/naranja", "seller": null, "price": "95.174", "reviews_rating_number": null, "reviews_amount": null},
{"name": "Aspiradora Ultracomb As4220 Filtro Hepa 1,2 Litros 1600w", "seller": "Por IOW Insumos Odontologicos Web ", "price": "113.000", "reviews_rating_number": null, "reviews_amount": null},
{"name": "Aspiradora Ultracomb As-4220 Sin Bolsa 1600w Filtro Hepa", "seller": null, "price": "123.573", "reviews_rating_number": null, "reviews_amount": null},
{"name": "Aspiradora Ultracomb As-4220 Sin Bolsa 1600w Filtro Hepa Ep", "seller": null, "price": "145.000", "reviews_rating_number": null, "reviews_amount": null}
]